{"actions": [{"id": 0, "dependency_ids": [], "name": "SetTool", "namespace": "/", "parameters": {"tool_name": "tool0"}}, {"id": 1, "dependency_ids": [], "name": "SetWorkObject", "namespace": "/", "parameters": {"wobj_name": "wobj0"}}, {"id": 2, "dependency_ids": [], "name": "MoveToJoints", "namespace": "/", "parameters": {"zone": -1, "speed": 100.0, "ext_axes": [], "feedback_level": 1, "joints": [-66.806878912253978, 9.2246205016062532, 49.560849278816207, 180.59629702523549, -31.054312496090620, 113.38834765638993]}}, {"id": 3, "dependency_ids": [], "name": "SetDigital", "namespace": "/", "parameters": {"io_name": "Local_IO_0_DO1", "value": 1}}, {"id": 4, "dependency_ids": [], "name": "MoveToFrame", "namespace": "/", "parameters": {"zone": -1, "speed": 100.0, "feedback_level": 1, "frame": {"guid": "645d6a3f-9677-4b84-a6d4-eaf4bb4a8962", "dtype": "compas.geometry/Frame", "value": {"point": [407.53655239936285, -726.55403178630013, 523.90496082486743], "yaxis": [-0.029644626094640483, 0.99956036920479363, -0.00051425566182146322], "xaxis": [-0.99954316685813371, -0.029647138019786797, -0.0058740781786426697]}}, "motion_type": "rrc.Motion.LINEAR"}}, {"id": 5, "dependency_ids": [], "name": "MoveToFrame", "namespace": "/", "parameters": {"zone": -1, "speed": 100.0, "feedback_level": 1, "frame": {"guid": "b69bfff8-5c36-4edd-b22a-a5564b7d111d", "dtype": "compas.geometry/Frame", "value": {"point": [408.71390079167628, -726.62200896260720, 323.90843778042398], "yaxis": [-0.029644626094640483, 0.99956036920479363, -0.00051425566182146322], "xaxis": [-0.99954316685813371, -0.029647138019786797, -0.0058740781786426697]}}, "motion_type": "rrc.Motion.LINEAR"}}, {"id": 6, "dependency_ids": [], "name": "WaitTime", "namespace": "/", "parameters": {"time": 1, "feedback_level": 1}}, {"id": 7, "dependency_ids": [], "name": "SetDigital", "namespace": "/", "parameters": {"io_name": "Local_IO_0_DO1", "value": 0}}, {"id": 8, "dependency_ids": [], "name": "PrintText", "namespace": "/", "parameters": {"text": "Screw the beam to the gripper!"}}, {"id": 9, "dependency_ids": [], "name": "Stop", "namespace": "/", "parameters": {}}, {"id": 10, "dependency_ids": [], "name": "MoveToFrame", "namespace": "/", "parameters": {"zone": -1, "speed": 100.0, "feedback_level": 1, "frame": {"guid": "21bfae66-ced4-4287-b565-7077f1f32e53", "dtype": "compas.geometry/Frame", "value": {"point": [407.53655239936285, -726.55403178630013, 523.90496082486743], "yaxis": [-0.029644626094640483, 0.99956036920479363, -0.00051425566182146322], "xaxis": [-0.99954316685813371, -0.029647138019786797, -0.0058740781786426697]}}, "motion_type": "rrc.Motion.LINEAR"}}, {"id": 11, "dependency_ids": [], "name": "PrintText", "namespace": "/", "parameters": {"text": "Robot goes to cut"}}, {"id": 12, "dependency_ids": [], "name": "Stop", "namespace": "/", "parameters": {}}, {"id": 13, "dependency_ids": [], "name": "MoveToJoints", "namespace": "/", "parameters": {"zone": 10, "speed": 100.0, "ext_axes": [], "feedback_level": 1, "joints": [-66.806878912253978, 9.2246205016062532, 49.560849278816207, 180.59629702523549, -31.054312496090620, 113.38834765638993]}}, {"id": 14, "dependency_ids": [], "name": "MoveToJoints", "namespace": "/", "parameters": {"zone": 5, "speed": 100.0, "ext_axes": [], "feedback_level": 1, "joints": [-66.806878912253978, 9.2246205016062532, 49.560849278816207, 180.59629702523549, -31.054312496090620, 113.38834765638993]}}, {"id": 15, "dependency_ids": [], "name": "MoveToJoints", "namespace": "/", "parameters": {"zone": 5, "speed": 100.0, "ext_axes": [], "feedback_level": 1, "joints": [-65.821242999924067, 9.6886690286148109, 48.294602866649043, 187.48600029978951, -27.852936087232486, 113.08322097123536]}}, {"id": 16, "dependency_ids": [], "name": "MoveToJoints", "namespace": "/", "parameters": {"zone": 5, "speed": 100.0, "ext_axes": [], "feedback_level": 1, "joints": [-64.835607087594155, 10.152717555623365, 47.028356454481873, 194.37570357434353, -24.651559678374348, 112.77809428608079]}}, {"id": 17, "dependency_ids": [], "name": "MoveToJoints", "namespace": "/", "parameters": {"zone": 5, "speed": 100.0, "ext_axes": [], "feedback_level": 1, "joints": [-63.849971175264230, 10.616766082631921, 45.762110042314703, 201.26540684889758, -21.450183269516209, 112.47296760092622]}}, {"id": 18, "dependency_ids": [], "name": "MoveToJoints", "namespace": "/", "parameters": {"zone": 5, "speed": 100.0, "ext_axes": [], "feedback_level": 1, "joints": [-62.864335262934318, 11.080814609640479, 44.495863630147539, 208.15511012345161, -18.248806860658075, 112.16784091577166]}}, {"id": 19, "dependency_ids": [], "name": "MoveToJoints", "namespace": "/", "parameters": {"zone": 5, "speed": 100.0, "ext_axes": [], "feedback_level": 1, "joints": [-61.878699350604400, 11.544863136649033, 43.229617217980369, 215.04481339800563, -15.047430451799935, 111.86271423061712]}}, {"id": 20, "dependency_ids": [], "name": "MoveToJoints", "namespace": "/", "parameters": {"zone": 5, "speed": 100.0, "ext_axes": [], "feedback_level": 1, "joints": [-60.893063438274481, 12.008911663657589, 41.963370805813199, 221.93451667255965, -11.846054042941800, 111.55758754546255]}}, {"id": 21, "dependency_ids": [], "name": "MoveToJoints", "namespace": "/", "parameters": {"zone": 5, "speed": 100.0, "ext_axes": [], "feedback_level": 1, "joints": [-59.907427525944556, 12.472960190666145, 40.697124393646035, 228.82421994711368, -8.6446776340836653, 111.25246086030799]}}, {"id": 22, "dependency_ids": [], "name": "MoveToJoints", "namespace": "/", "parameters": {"zone": 5, "speed": 100.0, "ext_axes": [], "feedback_level": 1, "joints": [-58.921791613614637, 12.937008717674701, 39.430877981478865, 235.71392322166773, -5.4433012252255262, 110.94733417515343]}}, {"id": 23, "dependency_ids": [], "name": "MoveToJoints", "namespace": "/", "parameters": {"zone": 5, "speed": 100.0, "ext_axes": [], "feedback_level": 1, "joints": [-57.936155701284719, 13.401057244683257, 38.164631569311702, 242.60362649622169, -2.2419248163673910, 110.64220748999885]}}, {"id": 24, "dependency_ids": [], "name": "MoveToJoints", "namespace": "/", "parameters": {"zone": 5, "speed": 100.0, "ext_axes": [], "feedback_level": 1, "joints": [-56.950519788954807, 13.865105771691812, 36.898385157144538, 249.49332977077577, 0.95945159249075063, 110.33708080484429]}}, {"id": 25, "dependency_ids": [], "name": "MoveToJoints", "namespace": "/", "parameters": {"zone": 5, "speed": 100.0, "ext_axes": [], "feedback_level": 1, "joints": [-55.964883876624889, 14.329154298700368, 35.632138744977368, 256.38303304532974, 4.1608280013488796, 110.03195411968973]}}, {"id": 26, "dependency_ids": [], "name": "MoveToJoints", "namespace": "/", "parameters": {"zone": 5, "speed": 100.0, "ext_axes": [], "feedback_level": 1, "joints": [-54.979247964294970, 14.793202825708926, 34.365892332810198, 263.27273631988385, 7.3622044102070214, 109.72682743453517]}}, {"id": 27, "dependency_ids": [], "name": "MoveToJoints", "namespace": "/", "parameters": {"zone": 5, "speed": 100.0, "ext_axes": [], "feedback_level": 1, "joints": [-53.993612051965052, 15.257251352717480, 33.099645920643034, 270.16243959443784, 10.563580819065157, 109.42170074938061]}}, {"id": 28, "dependency_ids": [], "name": "MoveToJoints", "namespace": "/", "parameters": {"zone": 5, "speed": 100.0, "ext_axes": [], "feedback_level": 1, "joints": [-53.007976139635140, 15.721299879726036, 31.833399508475864, 277.05214286899184, 13.764957227923292, 109.11657406422606]}}, {"id": 29, "dependency_ids": [], "name": "MoveToJoints", "namespace": "/", "parameters": {"zone": 5, "speed": 100.0, "ext_axes": [], "feedback_level": 1, "joints": [-52.022340227305222, 16.185348406734590, 30.567153096308697, 283.94184614354589, 16.966333636781428, 108.81144737907150]}}, {"id": 30, "dependency_ids": [], "name": "MoveToJoints", "namespace": "/", "parameters": {"zone": 5, "speed": 100.0, "ext_axes": [], "feedback_level": 1, "joints": [-51.036704314975303, 16.649396933743148, 29.300906684141527, 290.83154941809988, 20.167710045639570, 108.50632069391693]}}, {"id": 31, "dependency_ids": [], "name": "MoveToJoints", "namespace": "/", "parameters": {"zone": 5, "speed": 100.0, "ext_axes": [], "feedback_level": 1, "joints": [-50.051068402645384, 17.113445460751702, 28.034660271974360, 297.72125269265393, 23.369086454497705, 108.20119400876236]}}, {"id": 32, "dependency_ids": [], "name": "MoveToJoints", "namespace": "/", "parameters": {"zone": 5, "speed": 100.0, "ext_axes": [], "feedback_level": 1, "joints": [-49.065432490315473, 17.577493987760260, 26.768413859807193, 304.61095596720799, 26.570462863355839, 107.89606732360780]}}, {"id": 33, "dependency_ids": [], "name": "MoveToJoints", "namespace": "/", "parameters": {"zone": 5, "speed": 100.0, "ext_axes": [], "feedback_level": 1, "joints": [-48.079796577985547, 18.041542514768814, 25.502167447640030, 311.50065924176198, 29.771839272213967, 107.59094063845323]}}, {"id": 34, "dependency_ids": [], "name": "MoveToJoints", "namespace": "/", "parameters": {"zone": 5, "speed": 100.0, "ext_axes": [], "feedback_level": 1, "joints": [-47.094160665655629, 18.505591041777372, 24.235921035472856, 318.39036251631603, 32.973215681072119, 107.28581395329867]}}, {"id": 35, "dependency_ids": [], "name": "MoveToJoints", "namespace": "/", "parameters": {"zone": 5, "speed": 100.0, "ext_axes": [], "feedback_level": 1, "joints": [-46.108524753325710, 18.969639568785929, 22.969674623305689, 325.28006579087003, 36.174592089930250, 106.98068726814411]}}, {"id": 36, "dependency_ids": [], "name": "MoveToJoints", "namespace": "/", "parameters": {"zone": 5, "speed": 100.0, "ext_axes": [], "feedback_level": 1, "joints": [-45.122888840995792, 19.433688095794480, 21.703428211138526, 332.16976906542408, 39.375968498788382, 106.67556058298956]}}, {"id": 37, "dependency_ids": [], "name": "MoveToJoints", "namespace": "/", "parameters": {"zone": 5, "speed": 100.0, "ext_axes": [], "feedback_level": 1, "joints": [-44.137252928665873, 19.897736622803038, 20.437181798971359, 339.05947233997813, 42.577344907646520, 106.37043389783500]}}, {"id": 38, "dependency_ids": [], "name": "MoveToJoints", "namespace": "/", "parameters": {"zone": 5, "speed": 100.0, "ext_axes": [], "feedback_level": 1, "joints": [-43.151617016335962, 20.361785149811595, 19.170935386804185, 345.94917561453212, 45.778721316504665, 106.06530721268044]}}, {"id": 39, "dependency_ids": [], "name": "MoveToJoints", "namespace": "/", "parameters": {"zone": 5, "speed": 100.0, "ext_axes": [], "feedback_level": 1, "joints": [-42.165981104006043, 20.825833676820150, 17.904688974637018, 352.83887888908617, 48.980097725362803, 105.76018052752586]}}, {"id": 40, "dependency_ids": [], "name": "MoveToJoints", "namespace": "/", "parameters": {"zone": 5, "speed": 100.0, "ext_axes": [], "feedback_level": 1, "joints": [-41.180345191676125, 21.289882203828707, 16.638442562469855, 359.72858216364023, 52.181474134220927, 105.45505384237130]}}, {"id": 41, "dependency_ids": [], "name": "MoveToJoints", "namespace": "/", "parameters": {"zone": -1, "speed": 100.0, "ext_axes": [], "feedback_level": 1, "joints": [-41.253828801270529, 21.740197287671432, 16.797370920931563, 360.26242491865617, 51.193797434109449, 105.12203954041560]}}, {"id": 42, "dependency_ids": [], "name": "MoveToFrame", "namespace": "/", "parameters": {"zone": -1, "speed": 100.0, "feedback_level": 1, "frame": {"guid": "e78c73f4-9d29-417d-8d93-8143aa0fda68", "dtype": "compas.geometry/Frame", "value": {"point": [1063.1942415351230, -949.16722517839264, 693.36167711831558], "yaxis": [0.99122237141121317, 0.1320783217565234, 0.0057902794329282477], "xaxis": [-0.13207405757002036, 0.99123922511146012, -0.0011144134884018202]}}, "motion_type": "rrc.Motion.LINEAR"}}, {"id": 43, "dependency_ids": [], "name": "MoveToFrame", "namespace": "/", "parameters": {"zone": -1, "speed": 100.0, "feedback_level": 1, "frame": {"guid": "a8749588-ec7d-4928-90c4-aaf93349e46a", "dtype": "compas.geometry/Frame", "value": {"point": [1063.4885786332011, -949.18421947246941, 643.36254635720468], "yaxis": [0.99122237141121317, 0.1320783217565234, 0.0057902794329282477], "xaxis": [-0.13207405757002036, 0.99123922511146012, -0.0011144134884018202]}}, "motion_type": "rrc.Motion.LINEAR"}}, {"id": 44, "dependency_ids": [], "name": "PrintText", "namespace": "/", "parameters": {"text": "Start Cutting Side A-1?"}}, {"id": 45, "dependency_ids": [], "name": "Stop", "namespace": "/", "parameters": {}}, {"id": 46, "dependency_ids": [], "name": "MoveToFrame", "namespace": "/", "parameters": {"zone": -1, "speed": 100.0, "feedback_level": 1, "frame": {"guid": "2f0b1f12-41b2-41a0-b6ae-1edbb8e218da", "dtype": "compas.geometry/Frame", "value": {"point": [1292.1012227880062, -1277.4130040225750, 644.81991566831891], "yaxis": [0.99122237141121317, 0.1320783217565234, 0.0057902794329282477], "xaxis": [-0.13207405757002036, 0.99123922511146012, -0.0011144134884018202]}}, "motion_type": "rrc.Motion.LINEAR"}}, {"id": 47, "dependency_ids": [], "name": "MoveToFrame", "namespace": "/", "parameters": {"zone": -1, "speed": 100.0, "feedback_level": 1, "frame": {"guid": "e705c4fa-1fe4-46b8-8ecf-a4ab7a53d53b", "dtype": "compas.geometry/Frame", "value": {"point": [1291.8068856899281, -1277.3960097284983, 694.81904642942970], "yaxis": [0.99122237141121317, 0.1320783217565234, 0.0057902794329282477], "xaxis": [-0.13207405757002036, 0.99123922511146012, -0.0011144134884018202]}}, "motion_type": "rrc.Motion.LINEAR"}}, {"id": 48, "dependency_ids": [], "name": "MoveToJoints", "namespace": "/", "parameters": {"zone": 5, "speed": 100.0, "ext_axes": [], "feedback_level": 1, "joints": [-45.796489137455062, 52.982226388937065, -36.921365378639088, 360.23460842038617, 73.687379835145947, 100.67793637534355]}}, {"id": 49, "dependency_ids": [], "name": "MoveToJoints", "namespace": "/", "parameters": {"zone": 5, "speed": 100.0, "ext_axes": [], "feedback_level": 1, "joints": [-46.020275085424913, 53.055256011462617, -37.597295281423044, 352.45067600334369, 72.970548521170883, 97.630784252533829]}}, {"id": 50, "dependency_ids": [], "name": "MoveToJoints", "namespace": "/", "parameters": {"zone": 5, "speed": 100.0, "ext_axes": [], "feedback_level": 1, "joints": [-46.244061033394772, 53.128285633988163, -38.273225184207014, 344.66674358630115, 72.253717207195820, 94.583632129724108]}}, {"id": 51, "dependency_ids": [], "name": "MoveToJoints", "namespace": "/", "parameters": {"zone": 5, "speed": 100.0, "ext_axes": [], "feedback_level": 1, "joints": [-46.467846981364623, 53.201315256513723, -38.949155086990970, 336.88281116925867, 71.536885893220756, 91.536480006914388]}}, {"id": 52, "dependency_ids": [], "name": "MoveToJoints", "namespace": "/", "parameters": {"zone": 5, "speed": 100.0, "ext_axes": [], "feedback_level": 1, "joints": [-46.691632929334467, 53.274344879039276, -39.625084989774933, 329.09887875221619, 70.820054579245692, 88.489327884104668]}}, {"id": 53, "dependency_ids": [], "name": "MoveToJoints", "namespace": "/", "parameters": {"zone": 5, "speed": 100.0, "ext_axes": [], "feedback_level": 1, "joints": [-46.915418877304326, 53.347374501564822, -40.301014892558889, 321.31494633517377, 70.103223265270628, 85.442175761294948]}}, {"id": 54, "dependency_ids": [], "name": "MoveToJoints", "namespace": "/", "parameters": {"zone": 5, "speed": 100.0, "ext_axes": [], "feedback_level": 1, "joints": [-47.139204825274177, 53.420404124090375, -40.976944795342845, 313.53101391813129, 69.386391951295550, 82.395023638485227]}}, {"id": 55, "dependency_ids": [], "name": "MoveToJoints", "namespace": "/", "parameters": {"zone": 5, "speed": 100.0, "ext_axes": [], "feedback_level": 1, "joints": [-47.362990773244036, 53.493433746615928, -41.652874698126809, 305.74708150108876, 68.669560637320487, 79.347871515675507]}}, {"id": 56, "dependency_ids": [], "name": "MoveToJoints", "namespace": "/", "parameters": {"zone": 5, "speed": 100.0, "ext_axes": [], "feedback_level": 1, "joints": [-47.586776721213887, 53.566463369141481, -42.328804600910765, 297.96314908404628, 67.952729323345409, 76.300719392865787]}}, {"id": 57, "dependency_ids": [], "name": "MoveToJoints", "namespace": "/", "parameters": {"zone": 5, "speed": 100.0, "ext_axes": [], "feedback_level": 1, "joints": [-47.810562669183739, 53.639492991667034, -43.004734503694728, 290.17921666700380, 67.235898009370345, 73.253567270056067]}}, {"id": 58, "dependency_ids": [], "name": "MoveToJoints", "namespace": "/", "parameters": {"zone": 5, "speed": 100.0, "ext_axes": [], "feedback_level": 1, "joints": [-48.034348617153590, 53.712522614192586, -43.680664406478691, 282.39528424996126, 66.519066695395281, 70.206415147246361]}}, {"id": 59, "dependency_ids": [], "name": "MoveToJoints", "namespace": "/", "parameters": {"zone": 5, "speed": 100.0, "ext_axes": [], "feedback_level": 1, "joints": [-48.258134565123441, 53.785552236718139, -44.356594309262647, 274.61135183291879, 65.802235381420218, 67.159263024436626]}}, {"id": 60, "dependency_ids": [], "name": "MoveToJoints", "namespace": "/", "parameters": {"zone": 5, "speed": 100.0, "ext_axes": [], "feedback_level": 1, "joints": [-48.481920513093300, 53.858581859243685, -45.032524212046610, 266.82741941587636, 65.085404067445154, 64.112110901626906]}}, {"id": 61, "dependency_ids": [], "name": "MoveToJoints", "namespace": "/", "parameters": {"zone": 5, "speed": 100.0, "ext_axes": [], "feedback_level": 1, "joints": [-48.705706461063151, 53.931611481769238, -45.708454114830566, 259.04348699883388, 64.368572753470090, 61.064958778817186]}}, {"id": 62, "dependency_ids": [], "name": "MoveToJoints", "namespace": "/", "parameters": {"zone": 5, "speed": 100.0, "ext_axes": [], "feedback_level": 1, "joints": [-48.336904625643974, 52.304181096631794, -42.622556543771431, 264.07441902339156, 63.687072199771791, 63.241014017775356]}}, {"id": 63, "dependency_ids": [], "name": "MoveToJoints", "namespace": "/", "parameters": {"zone": 5, "speed": 100.0, "ext_axes": [], "feedback_level": 1, "joints": [-47.968102790224812, 50.676750711494343, -39.536658972712296, 269.10535104794934, 63.005571646073484, 65.417069256733527]}}, {"id": 64, "dependency_ids": [], "name": "MoveToJoints", "namespace": "/", "parameters": {"zone": 5, "speed": 100.0, "ext_axes": [], "feedback_level": 1, "joints": [-47.599300954805642, 49.049320326356906, -36.450761401653168, 274.13628307250713, 62.324071092375185, 67.593124495691697]}}, {"id": 65, "dependency_ids": [], "name": "MoveToJoints", "namespace": "/", "parameters": {"zone": 5, "speed": 100.0, "ext_axes": [], "feedback_level": 1, "joints": [-47.230499119386465, 47.421889941219455, -33.364863830594025, 279.16721509706480, 61.642570538676885, 69.769179734649853]}}, {"id": 66, "dependency_ids": [], "name": "MoveToJoints", "namespace": "/", "parameters": {"zone": 5, "speed": 100.0, "ext_axes": [], "feedback_level": 1, "joints": [-46.861697283967288, 45.794459556082010, -30.278966259534897, 284.19814712162253, 60.961069984978579, 71.945234973608024]}}, {"id": 67, "dependency_ids": [], "name": "MoveToJoints", "namespace": "/", "parameters": {"zone": 5, "speed": 100.0, "ext_axes": [], "feedback_level": 1, "joints": [-46.492895448548126, 44.167029170944566, -27.193068688475762, 289.22907914618031, 60.279569431280279, 74.121290212566194]}}, {"id": 68, "dependency_ids": [], "name": "MoveToJoints", "namespace": "/", "parameters": {"zone": 5, "speed": 100.0, "ext_axes": [], "feedback_level": 1, "joints": [-46.124093613128956, 42.539598785807122, -24.107171117416627, 294.26001117073804, 59.598068877581980, 76.297345451524365]}}, {"id": 69, "dependency_ids": [], "name": "MoveToJoints", "namespace": "/", "parameters": {"zone": 5, "speed": 100.0, "ext_axes": [], "feedback_level": 1, "joints": [-45.755291777709779, 40.912168400669671, -21.021273546357488, 299.29094319529577, 58.916568323883688, 78.473400690482535]}}, {"id": 70, "dependency_ids": [], "name": "MoveToJoints", "namespace": "/", "parameters": {"zone": 5, "speed": 100.0, "ext_axes": [], "feedback_level": 1, "joints": [-45.386489942290602, 39.284738015532227, -17.935375975298353, 304.32187521985350, 58.235067770185374, 80.649455929440705]}}, {"id": 71, "dependency_ids": [], "name": "MoveToJoints", "namespace": "/", "parameters": {"zone": 5, "speed": 100.0, "ext_axes": [], "feedback_level": 1, "joints": [-45.017688106871439, 37.657307630394776, -14.849478404239221, 309.35280724441122, 57.553567216487075, 82.825511168398862]}}, {"id": 72, "dependency_ids": [], "name": "MoveToJoints", "namespace": "/", "parameters": {"zone": 5, "speed": 100.0, "ext_axes": [], "feedback_level": 1, "joints": [-44.648886271452270, 36.029877245257339, -11.763580833180084, 314.38373926896901, 56.872066662788775, 85.001566407357032]}}, {"id": 73, "dependency_ids": [], "name": "MoveToJoints", "namespace": "/", "parameters": {"zone": 5, "speed": 100.0, "ext_axes": [], "feedback_level": 1, "joints": [-44.280084436033093, 34.402446860119888, -8.6776832621209543, 319.41467129352674, 56.190566109090476, 87.177621646315202]}}, {"id": 74, "dependency_ids": [], "name": "MoveToJoints", "namespace": "/", "parameters": {"zone": 5, "speed": 100.0, "ext_axes": [], "feedback_level": 1, "joints": [-43.911282600613916, 32.775016474982444, -5.5917856910618173, 324.44560331808441, 55.509065555392169, 89.353676885273373]}}, {"id": 75, "dependency_ids": [], "name": "MoveToJoints", "namespace": "/", "parameters": {"zone": 5, "speed": 100.0, "ext_axes": [], "feedback_level": 1, "joints": [-43.542480765194753, 31.147586089844999, -2.5058881200026875, 329.47653534264219, 54.827565001693877, 91.529732124231543]}}, {"id": 76, "dependency_ids": [], "name": "MoveToJoints", "namespace": "/", "parameters": {"zone": 5, "speed": 100.0, "ext_axes": [], "feedback_level": 1, "joints": [-43.173678929775583, 29.520155704707552, 0.58000945105645563, 334.50746736719998, 54.146064447995570, 93.705787363189700]}}, {"id": 77, "dependency_ids": [], "name": "MoveToJoints", "namespace": "/", "parameters": {"zone": 5, "speed": 100.0, "ext_axes": [], "feedback_level": 1, "joints": [-42.804877094356407, 27.892725319570104, 3.6659070221155923, 339.53839939175765, 53.464563894297271, 95.881842602147870]}}, {"id": 78, "dependency_ids": [], "name": "MoveToJoints", "namespace": "/", "parameters": {"zone": 5, "speed": 100.0, "ext_axes": [], "feedback_level": 1, "joints": [-42.436075258937237, 26.265294934432660, 6.7518045931747226, 344.56933141631538, 52.783063340598972, 98.057897841106040]}}, {"id": 79, "dependency_ids": [], "name": "MoveToJoints", "namespace": "/", "parameters": {"zone": 5, "speed": 100.0, "ext_axes": [], "feedback_level": 1, "joints": [-42.067273423518067, 24.637864549295212, 9.8377021642338587, 349.60026344087316, 52.101562786900665, 100.23395308006421]}}, {"id": 80, "dependency_ids": [], "name": "MoveToJoints", "namespace": "/", "parameters": {"zone": 5, "speed": 100.0, "ext_axes": [], "feedback_level": 1, "joints": [-41.698471588098897, 23.010434164157768, 12.923599735292989, 354.63119546543089, 51.420062233202373, 102.41000831902238]}}, {"id": 81, "dependency_ids": [], "name": "MoveToJoints", "namespace": "/", "parameters": {"zone": 5, "speed": 100.0, "ext_axes": [], "feedback_level": 1, "joints": [-41.329669752679720, 21.383003779020321, 16.009497306352124, 359.66212748998862, 50.738561679504066, 104.58606355798055]}}, {"id": 82, "dependency_ids": [], "name": "MoveToFrame", "namespace": "/", "parameters": {"zone": -1, "speed": 100.0, "feedback_level": 1, "frame": {"guid": "180d11b3-8731-459f-8591-be6a9251b845", "dtype": "compas.geometry/Frame", "value": {"point": [793.12908516590608, -867.42948756058684, 691.74406360510375], "yaxis": [0.5715316103870125, -0.82057196137526367, 0.0036434232777853869], "xaxis": [0.82055893426219317, 0.5715431223296632, 0.0046362398722901111]}}, "motion_type": "rrc.Motion.LINEAR"}}, {"id": 83, "dependency_ids": [], "name": "MoveToFrame", "namespace": "/", "parameters": {"zone": -1, "speed": 100.0, "feedback_level": 1, "frame": {"guid": "825fe15f-f7e2-4cb8-b9f0-490548d0eb8d", "dtype": "compas.geometry/Frame", "value": {"point": [793.42342226398421, -867.44648185466360, 641.74493284399284], "yaxis": [0.5715316103870125, -0.82057196137526367, 0.0036434232777853869], "xaxis": [0.82055893426219317, 0.5715431223296632, 0.0046362398722901111]}}, "motion_type": "rrc.Motion.LINEAR"}}, {"id": 84, "dependency_ids": [], "name": "PrintText", "namespace": "/", "parameters": {"text": "Start Cutting Side A-2?"}}, {"id": 85, "dependency_ids": [], "name": "Stop", "namespace": "/", "parameters": {}}, {"id": 86, "dependency_ids": [], "name": "MoveToFrame", "namespace": "/", "parameters": {"zone": -1, "speed": 100.0, "feedback_level": 1, "frame": {"guid": "5443dd53-775d-4a0b-8944-db9a6bf85e17", "dtype": "compas.geometry/Frame", "value": {"point": [1136.3423884961917, -1359.7896586798220, 643.93098681066419], "yaxis": [0.5715316103870125, -0.82057196137526367, 0.0036434232777853869], "xaxis": [0.82055893426219317, 0.5715431223296632, 0.0046362398722901111]}}, "motion_type": "rrc.Motion.LINEAR"}}, {"id": 87, "dependency_ids": [], "name": "MoveToFrame", "namespace": "/", "parameters": {"zone": -1, "speed": 100.0, "feedback_level": 1, "frame": {"guid": "5afb5d65-8704-41b2-8524-7d4aa0b141cb", "dtype": "compas.geometry/Frame", "value": {"point": [1136.0480513981136, -1359.7726643857450, 693.93011757177487], "yaxis": [0.5715316103870125, -0.82057196137526367, 0.0036434232777853869], "xaxis": [0.82055893426219317, 0.5715431223296632, 0.0046362398722901111]}}, "motion_type": "rrc.Motion.LINEAR"}}, {"id": 88, "dependency_ids": [], "name": "MoveToJoints", "namespace": "/", "parameters": {"zone": 5, "speed": 100.0, "ext_axes": [], "feedback_level": 1, "joints": [-45.796489137455062, 52.982226388937065, -36.921365378639088, 360.23460842038617, 73.687379835145947, 100.67793637534355]}}, {"id": 89, "dependency_ids": [], "name": "MoveToJoints", "namespace": "/", "parameters": {"zone": 5, "speed": 100.0, "ext_axes": [], "feedback_level": 1, "joints": [-45.821161322918243, 52.370107172381587, -36.698403371948537, 351.75357323704827, 71.259582525532892, 99.232196370903580]}}, {"id": 90, "dependency_ids": [], "name": "MoveToJoints", "namespace": "/", "parameters": {"zone": 5, "speed": 100.0, "ext_axes": [], "feedback_level": 1, "joints": [-45.845833508381418, 51.757987955826117, -36.475441365257993, 343.27253805371043, 68.831785215919837, 97.786456366463611]}}, {"id": 91, "dependency_ids": [], "name": "MoveToJoints", "namespace": "/", "parameters": {"zone": 5, "speed": 100.0, "ext_axes": [], "feedback_level": 1, "joints": [-45.870505693844592, 51.145868739270639, -36.252479358567442, 334.79150287037254, 66.403987906306767, 96.340716362023656]}}, {"id": 92, "dependency_ids": [], "name": "MoveToJoints", "namespace": "/", "parameters": {"zone": 5, "speed": 100.0, "ext_axes": [], "feedback_level": 1, "joints": [-45.895177879307774, 50.533749522715169, -36.029517351876898, 326.31046768703470, 63.976190596693712, 94.894976357583687]}}, {"id": 93, "dependency_ids": [], "name": "MoveToJoints", "namespace": "/", "parameters": {"zone": 5, "speed": 100.0, "ext_axes": [], "feedback_level": 1, "joints": [-45.919850064770955, 49.921630306159692, -35.806555345186347, 317.82943250369681, 61.548393287080650, 93.449236353143718]}}, {"id": 94, "dependency_ids": [], "name": "MoveToJoints", "namespace": "/", "parameters": {"zone": 5, "speed": 100.0, "ext_axes": [], "feedback_level": 1, "joints": [-45.944522250234130, 49.309511089604214, -35.583593338495803, 309.34839732035897, 59.120595977467602, 92.003496348703777]}}, {"id": 95, "dependency_ids": [], "name": "MoveToJoints", "namespace": "/", "parameters": {"zone": 5, "speed": 100.0, "ext_axes": [], "feedback_level": 1, "joints": [-45.969194435697311, 48.697391873048744, -35.360631331805251, 300.86736213702108, 56.692798667854547, 90.557756344263808]}}, {"id": 96, "dependency_ids": [], "name": "MoveToJoints", "namespace": "/", "parameters": {"zone": 5, "speed": 100.0, "ext_axes": [], "feedback_level": 1, "joints": [-45.993866621160493, 48.085272656493267, -35.137669325114707, 292.38632695368329, 54.265001358241484, 89.112016339823839]}}, {"id": 97, "dependency_ids": [], "name": "MoveToJoints", "namespace": "/", "parameters": {"zone": 5, "speed": 100.0, "ext_axes": [], "feedback_level": 1, "joints": [-46.018538806623667, 47.473153439937796, -34.914707318424156, 283.90529177034540, 51.837204048628422, 87.666276335383884]}}, {"id": 98, "dependency_ids": [], "name": "MoveToJoints", "namespace": "/", "parameters": {"zone": 5, "speed": 100.0, "ext_axes": [], "feedback_level": 1, "joints": [-46.043210992086848, 46.861034223382319, -34.691745311733612, 275.42425658700756, 49.409406739015360, 86.220536330943915]}}, {"id": 99, "dependency_ids": [], "name": "MoveToJoints", "namespace": "/", "parameters": {"zone": 5, "speed": 100.0, "ext_axes": [], "feedback_level": 1, "joints": [-46.067883177550030, 46.248915006826842, -34.468783305043061, 266.94322140366967, 46.981609429402305, 84.774796326503946]}}, {"id": 100, "dependency_ids": [], "name": "MoveToJoints", "namespace": "/", "parameters": {"zone": 5, "speed": 100.0, "ext_axes": [], "feedback_level": 1, "joints": [-46.092555363013211, 45.636795790271371, -34.245821298352510, 258.46218622033177, 44.553812119789249, 83.329056322063991]}}, {"id": 101, "dependency_ids": [], "name": "MoveToJoints", "namespace": "/", "parameters": {"zone": 5, "speed": 100.0, "ext_axes": [], "feedback_level": 1, "joints": [-46.117227548476386, 45.024676573715894, -34.022859291661959, 249.98115103699394, 42.126014810176180, 81.883316317624022]}}, {"id": 102, "dependency_ids": [], "name": "MoveToJoints", "namespace": "/", "parameters": {"zone": 5, "speed": 100.0, "ext_axes": [], "feedback_level": 1, "joints": [-46.141899733939560, 44.412557357160416, -33.799897284971408, 241.50011585365610, 39.698217500563125, 80.437576313184067]}}, {"id": 103, "dependency_ids": [], "name": "MoveToJoints", "namespace": "/", "parameters": {"zone": 5, "speed": 100.0, "ext_axes": [], "feedback_level": 1, "joints": [-46.166571919402742, 43.800438140604939, -33.576935278280864, 233.01908067031820, 37.270420190950070, 78.991836308744112]}}, {"id": 104, "dependency_ids": [], "name": "MoveToJoints", "namespace": "/", "parameters": {"zone": 5, "speed": 100.0, "ext_axes": [], "feedback_level": 1, "joints": [-46.191244104865916, 43.188318924049469, -33.353973271590313, 224.53804548698037, 34.842622881337007, 77.546096304304143]}}, {"id": 105, "dependency_ids": [], "name": "MoveToJoints", "namespace": "/", "parameters": {"zone": 5, "speed": 100.0, "ext_axes": [], "feedback_level": 1, "joints": [-46.215916290329098, 42.576199707493991, -33.131011264899769, 216.05701030364247, 32.414825571723945, 76.100356299864174]}}, {"id": 106, "dependency_ids": [], "name": "MoveToJoints", "namespace": "/", "parameters": {"zone": 5, "speed": 100.0, "ext_axes": [], "feedback_level": 1, "joints": [-46.240588475792279, 41.964080490938521, -32.908049258209218, 207.57597512030463, 29.987028262110893, 74.654616295424219]}}, {"id": 107, "dependency_ids": [], "name": "MoveToJoints", "namespace": "/", "parameters": {"zone": 5, "speed": 100.0, "ext_axes": [], "feedback_level": 1, "joints": [-46.265260661255461, 41.351961274383044, -32.685087251518674, 199.09493993696674, 27.559230952497835, 73.208876290984250]}}, {"id": 108, "dependency_ids": [], "name": "MoveToJoints", "namespace": "/", "parameters": {"zone": 5, "speed": 100.0, "ext_axes": [], "feedback_level": 1, "joints": [-46.289932846718635, 40.739842057827566, -32.462125244828123, 190.61390475362887, 25.131433642884772, 71.763136286544281]}}, {"id": 109, "dependency_ids": [], "name": "MoveToJoints", "namespace": "/", "parameters": {"zone": 5, "speed": 100.0, "ext_axes": [], "feedback_level": 1, "joints": [-46.314605032181817, 40.127722841272089, -32.239163238137571, 182.13286957029104, 22.703636333271714, 70.317396282104326]}}, {"id": 110, "dependency_ids": [], "name": "MoveToJoints", "namespace": "/", "parameters": {"zone": 5, "speed": 100.0, "ext_axes": [], "feedback_level": 1, "joints": [-46.339277217644998, 39.515603624716618, -32.016201231447027, 173.65183438695317, 20.275839023658651, 68.871656277664357]}}, {"id": 111, "dependency_ids": [], "name": "MoveToJoints", "namespace": "/", "parameters": {"zone": 5, "speed": 100.0, "ext_axes": [], "feedback_level": 1, "joints": [-46.363949403108172, 38.903484408161141, -31.793239224756476, 165.17079920361527, 17.848041714045593, 67.425916273224388]}}, {"id": 112, "dependency_ids": [], "name": "MoveToJoints", "namespace": "/", "parameters": {"zone": 5, "speed": 100.0, "ext_axes": [], "feedback_level": 1, "joints": [-46.388621588571354, 38.291365191605671, -31.570277218065929, 156.68976402027744, 15.420244404432545, 65.980176268784433]}}, {"id": 113, "dependency_ids": [], "name": "MoveToJoints", "namespace": "/", "parameters": {"zone": 5, "speed": 100.0, "ext_axes": [], "feedback_level": 1, "joints": [-46.413293774034535, 37.679245975050193, -31.347315211375378, 148.20872883693957, 12.992447094819472, 64.534436264344464]}}, {"id": 114, "dependency_ids": [], "name": "MoveToJoints", "namespace": "/", "parameters": {"zone": 5, "speed": 100.0, "ext_axes": [], "feedback_level": 1, "joints": [-46.437965959497710, 37.067126758494716, -31.124353204684834, 139.72769365360170, 10.564649785206411, 63.088696259904502]}}, {"id": 115, "dependency_ids": [], "name": "MoveToJoints", "namespace": "/", "parameters": {"zone": 5, "speed": 100.0, "ext_axes": [], "feedback_level": 1, "joints": [-46.462638144960884, 36.455007541939239, -30.901391197994283, 131.24665847026384, 8.1368524755933525, 61.642956255464533]}}, {"id": 116, "dependency_ids": [], "name": "MoveToJoints", "namespace": "/", "parameters": {"zone": 5, "speed": 100.0, "ext_axes": [], "feedback_level": 1, "joints": [-46.487310330424066, 35.842888325383775, -30.678429191303739, 122.76562328692600, 5.7090551659803044, 60.197216251024585]}}, {"id": 117, "dependency_ids": [], "name": "MoveToJoints", "namespace": "/", "parameters": {"zone": 5, "speed": 100.0, "ext_axes": [], "feedback_level": 1, "joints": [-46.511982515887247, 35.230769108828298, -30.455467184613187, 114.28458810358811, 3.2812578563672439, 58.751476246584616]}}, {"id": 118, "dependency_ids": [], "name": "MoveToJoints", "namespace": "/", "parameters": {"zone": 5, "speed": 100.0, "ext_axes": [], "feedback_level": 1, "joints": [-46.536654701350422, 34.618649892272821, -30.232505177922643, 105.80355292025023, 0.8534605467541837, 57.305736242144654]}}, {"id": 119, "dependency_ids": [], "name": "MoveToJoints", "namespace": "/", "parameters": {"zone": 5, "speed": 100.0, "ext_axes": [], "feedback_level": 1, "joints": [-46.561326886813603, 34.006530675717343, -30.009543171232092, 97.322517736912388, -1.5743367628588765, 55.859996237704692]}}, {"id": 120, "dependency_ids": [], "name": "MoveToJoints", "namespace": "/", "parameters": {"zone": 5, "speed": 100.0, "ext_axes": [], "feedback_level": 1, "joints": [-46.585999072276785, 33.394411459161873, -29.786581164541541, 88.841482553574551, -4.0021340724719368, 54.414256233264723]}}, {"id": 121, "dependency_ids": [], "name": "MoveToJoints", "namespace": "/", "parameters": {"zone": 5, "speed": 100.0, "ext_axes": [], "feedback_level": 1, "joints": [-46.610671257739966, 32.782292242606403, -29.563619157850994, 80.360447370236670, -6.4299313820849973, 52.968516228824761]}}, {"id": 122, "dependency_ids": [], "name": "MoveToJoints", "namespace": "/", "parameters": {"zone": 5, "speed": 100.0, "ext_axes": [], "feedback_level": 1, "joints": [-46.635343443203141, 32.170173026050925, -29.340657151160443, 71.879412186898776, -8.8577286916980569, 51.522776224384799]}}, {"id": 123, "dependency_ids": [], "name": "MoveToJoints", "namespace": "/", "parameters": {"zone": 5, "speed": 100.0, "ext_axes": [], "feedback_level": 1, "joints": [-46.660015628666322, 31.558053809495448, -29.117695144469899, 63.398377003560945, -11.285526001311117, 50.077036219944830]}}, {"id": 124, "dependency_ids": [], "name": "MoveToJoints", "namespace": "/", "parameters": {"zone": 5, "speed": 100.0, "ext_axes": [], "feedback_level": 1, "joints": [-46.684687814129504, 30.945934592939974, -28.894733137779347, 54.917341820223108, -13.713323310924165, 48.631296215504875]}}, {"id": 125, "dependency_ids": [], "name": "MoveToJoints", "namespace": "/", "parameters": {"zone": 5, "speed": 100.0, "ext_axes": [], "feedback_level": 1, "joints": [-46.709359999592678, 30.333815376384500, -28.671771131088803, 46.436306636885220, -16.141120620537226, 47.185556211064913]}}, {"id": 126, "dependency_ids": [], "name": "MoveToJoints", "namespace": "/", "parameters": {"zone": 5, "speed": 100.0, "ext_axes": [], "feedback_level": 1, "joints": [-46.734032185055852, 29.721696159829026, -28.448809124398252, 37.955271453547333, -18.568917930150285, 45.739816206624944]}}, {"id": 127, "dependency_ids": [], "name": "MoveToJoints", "namespace": "/", "parameters": {"zone": 5, "speed": 100.0, "ext_axes": [], "feedback_level": 1, "joints": [-46.758704370519034, 29.109576943273549, -28.225847117707705, 29.474236270209449, -20.996715239763358, 44.294076202184982]}}, {"id": 128, "dependency_ids": [], "name": "MoveToJoints", "namespace": "/", "parameters": {"zone": 5, "speed": 100.0, "ext_axes": [], "feedback_level": 1, "joints": [-46.783376555982215, 28.497457726718075, -28.002885111017157, 20.993201086871611, -23.424512549376406, 42.848336197745027]}}, {"id": 129, "dependency_ids": [], "name": "MoveToJoints", "namespace": "/", "parameters": {"zone": 5, "speed": 100.0, "ext_axes": [], "feedback_level": 1, "joints": [-46.808048741445390, 27.885338510162597, -27.779923104326606, 12.512165903533777, -25.852309858989464, 41.402596193305058]}}, {"id": 130, "dependency_ids": [], "name": "MoveToJoints", "namespace": "/", "parameters": {"zone": 5, "speed": 100.0, "ext_axes": [], "feedback_level": 1, "joints": [-46.832720926908571, 27.273219293607124, -27.556961097636059, 4.0311307201958950, -28.280107168602527, 39.956856188865089]}}, {"id": 131, "dependency_ids": [], "name": "MoveToJoints", "namespace": "/", "parameters": {"zone": 5, "speed": 100.0, "ext_axes": [], "feedback_level": 1, "joints": [-46.634538264557634, 27.002808358713356, -25.762459149908921, 11.350221301575619, -29.329528645048523, 42.632860464909832]}}, {"id": 132, "dependency_ids": [], "name": "MoveToJoints", "namespace": "/", "parameters": {"zone": 5, "speed": 100.0, "ext_axes": [], "feedback_level": 1, "joints": [-46.436355602206689, 26.732397423819592, -23.967957202181779, 18.669311882955345, -30.378950121494512, 45.308864740954583]}}, {"id": 133, "dependency_ids": [], "name": "MoveToJoints", "namespace": "/", "parameters": {"zone": 5, "speed": 100.0, "ext_axes": [], "feedback_level": 1, "joints": [-46.238172939855751, 26.461986488925824, -22.173455254454641, 25.988402464335071, -31.428371597940508, 47.984869016999319]}}, {"id": 134, "dependency_ids": [], "name": "MoveToJoints", "namespace": "/", "parameters": {"zone": 5, "speed": 100.0, "ext_axes": [], "feedback_level": 1, "joints": [-46.039990277504806, 26.191575554032060, -20.378953306727503, 33.307493045714793, -32.477793074386504, 50.660873293044062]}}, {"id": 135, "dependency_ids": [], "name": "MoveToJoints", "namespace": "/", "parameters": {"zone": 5, "speed": 100.0, "ext_axes": [], "feedback_level": 1, "joints": [-45.841807615153868, 25.921164619138292, -18.584451359000365, 40.626583627094526, -33.527214550832497, 53.336877569088813]}}, {"id": 136, "dependency_ids": [], "name": "MoveToJoints", "namespace": "/", "parameters": {"zone": 5, "speed": 100.0, "ext_axes": [], "feedback_level": 1, "joints": [-45.643624952802931, 25.650753684244524, -16.789949411273223, 47.945674208474244, -34.576636027278489, 56.012881845133556]}}, {"id": 137, "dependency_ids": [], "name": "MoveToJoints", "namespace": "/", "parameters": {"zone": 5, "speed": 100.0, "ext_axes": [], "feedback_level": 1, "joints": [-45.445442290451986, 25.380342749350760, -14.995447463546082, 55.264764789853970, -35.626057503724489, 58.688886121178307]}}, {"id": 138, "dependency_ids": [], "name": "MoveToJoints", "namespace": "/", "parameters": {"zone": 5, "speed": 100.0, "ext_axes": [], "feedback_level": 1, "joints": [-45.247259628101041, 25.109931814456992, -13.200945515818944, 62.583855371233682, -36.675478980170482, 61.364890397223043]}}, {"id": 139, "dependency_ids": [], "name": "MoveToJoints", "namespace": "/", "parameters": {"zone": 5, "speed": 100.0, "ext_axes": [], "feedback_level": 1, "joints": [-45.049076965750103, 24.839520879563224, -11.406443568091806, 69.902945952613422, -37.724900456616481, 64.040894673267786]}}, {"id": 140, "dependency_ids": [], "name": "MoveToJoints", "namespace": "/", "parameters": {"zone": 5, "speed": 100.0, "ext_axes": [], "feedback_level": 1, "joints": [-44.850894303399159, 24.569109944669457, -9.6119416203646662, 77.222036533993148, -38.774321933062467, 66.716898949312537]}}, {"id": 141, "dependency_ids": [], "name": "MoveToJoints", "namespace": "/", "parameters": {"zone": 5, "speed": 100.0, "ext_axes": [], "feedback_level": 1, "joints": [-44.652711641048221, 24.298699009775689, -7.8174396726375273, 84.541127115372859, -39.823743409508467, 69.392903225357273]}}, {"id": 142, "dependency_ids": [], "name": "MoveToJoints", "namespace": "/", "parameters": {"zone": 5, "speed": 100.0, "ext_axes": [], "feedback_level": 1, "joints": [-44.454528978697283, 24.028288074881921, -6.0229377249103866, 91.860217696752585, -40.873164885954452, 72.068907501402023]}}, {"id": 143, "dependency_ids": [], "name": "MoveToJoints", "namespace": "/", "parameters": {"zone": 5, "speed": 100.0, "ext_axes": [], "feedback_level": 1, "joints": [-44.256346316346338, 23.757877139988157, -4.2284357771832486, 99.179308278132311, -41.922586362400452, 74.744911777446760]}}, {"id": 144, "dependency_ids": [], "name": "MoveToJoints", "namespace": "/", "parameters": {"zone": 5, "speed": 100.0, "ext_axes": [], "feedback_level": 1, "joints": [-44.058163653995400, 23.487466205094389, -2.4339338294561044, 106.49839885951205, -42.972007838846444, 77.420916053491510]}}, {"id": 145, "dependency_ids": [], "name": "MoveToJoints", "namespace": "/", "parameters": {"zone": 5, "speed": 100.0, "ext_axes": [], "feedback_level": 1, "joints": [-43.859980991644456, 23.217055270200621, -0.63943188172896659, 113.81748944089176, -44.021429315292444, 80.096920329536246]}}, {"id": 146, "dependency_ids": [], "name": "MoveToJoints", "namespace": "/", "parameters": {"zone": 5, "speed": 100.0, "ext_axes": [], "feedback_level": 1, "joints": [-43.661798329293518, 22.946644335306857, 1.1550700659981712, 121.13658002227147, -45.070850791738430, 82.772924605580997]}}, {"id": 147, "dependency_ids": [], "name": "MoveToJoints", "namespace": "/", "parameters": {"zone": 5, "speed": 100.0, "ext_axes": [], "feedback_level": 1, "joints": [-43.463615666942580, 22.676233400413089, 2.9495720137253154, 128.45567060365121, -46.120272268184429, 85.448928881625747]}}, {"id": 148, "dependency_ids": [], "name": "MoveToJoints", "namespace": "/", "parameters": {"zone": 5, "speed": 100.0, "ext_axes": [], "feedback_level": 1, "joints": [-43.265433004591635, 22.405822465519325, 4.7440739614524468, 135.77476118503094, -47.169693744630422, 88.124933157670483]}}, {"id": 149, "dependency_ids": [], "name": "MoveToJoints", "namespace": "/", "parameters": {"zone": 5, "speed": 100.0, "ext_axes": [], "feedback_level": 1, "joints": [-43.067250342240698, 22.135411530625557, 6.5385759091795848, 143.09385176641067, -48.219115221076414, 90.800937433715234]}}, {"id": 150, "dependency_ids": [], "name": "MoveToJoints", "namespace": "/", "parameters": {"zone": 5, "speed": 100.0, "ext_axes": [], "feedback_level": 1, "joints": [-42.869067679889753, 21.865000595731793, 8.3330778569067281, 150.41294234779042, -49.268536697522407, 93.476941709759970]}}, {"id": 151, "dependency_ids": [], "name": "MoveToJoints", "namespace": "/", "parameters": {"zone": 5, "speed": 100.0, "ext_axes": [], "feedback_level": 1, "joints": [-42.670885017538808, 21.594589660838025, 10.127579804633866, 157.73203292917012, -50.317958173968407, 96.152945985804720]}}, {"id": 152, "dependency_ids": [], "name": "MoveToJoints", "namespace": "/", "parameters": {"zone": 5, "speed": 100.0, "ext_axes": [], "feedback_level": 1, "joints": [-42.472702355187870, 21.324178725944257, 11.922081752361004, 165.05112351054984, -51.367379650414399, 98.828950261849442]}}, {"id": 153, "dependency_ids": [], "name": "MoveToJoints", "namespace": "/", "parameters": {"zone": 5, "speed": 100.0, "ext_axes": [], "feedback_level": 1, "joints": [-42.274519692836925, 21.053767791050490, 13.716583700088149, 172.37021409192957, -52.416801126860399, 101.50495453789421]}}, {"id": 154, "dependency_ids": [], "name": "MoveToJoints", "namespace": "/", "parameters": {"zone": 5, "speed": 100.0, "ext_axes": [], "feedback_level": 1, "joints": [-42.076337030485988, 20.783356856156722, 15.511085647815289, 179.68930467330929, -53.466222603306385, 104.18095881393894]}}, {"id": 155, "dependency_ids": [], "name": "MoveToJoints", "namespace": "/", "parameters": {"zone": -1, "speed": 100.0, "ext_axes": [], "feedback_level": 1, "joints": [-41.252961249419272, 20.511889065683469, 15.412564689019145, 180.25252234815699, -53.800736962784299, 105.13775540650606]}}, {"id": 156, "dependency_ids": [], "name": "MoveToFrame", "namespace": "/", "parameters": {"zone": -1, "speed": 100.0, "feedback_level": 1, "frame": {"guid": "989dfa17-11a8-41ca-9374-83d5e7b2e765", "dtype": "compas.geometry/Frame", "value": {"point": [793.12908516590471, -867.42948756058729, 691.74406360510375], "yaxis": [-0.57153161038701239, 0.82057196137526378, -0.0036434232777853874], "xaxis": [-0.82055893426219328, -0.57154312232966309, -0.0046362398722901111]}}, "motion_type": "rrc.Motion.LINEAR"}}, {"id": 157, "dependency_ids": [], "name": "MoveToFrame", "namespace": "/", "parameters": {"zone": -1, "speed": 100.0, "feedback_level": 1, "frame": {"guid": "9bad06a6-e7c8-4b93-9fff-087de13f28c8", "dtype": "compas.geometry/Frame", "value": {"point": [793.42342226398284, -867.44648185466394, 641.74493284399284], "yaxis": [-0.57153161038701239, 0.82057196137526378, -0.0036434232777853874], "xaxis": [-0.82055893426219328, -0.57154312232966309, -0.0046362398722901111]}}, "motion_type": "rrc.Motion.LINEAR"}}, {"id": 158, "dependency_ids": [], "name": "PrintText", "namespace": "/", "parameters": {"text": "Start Cutting Side B-1?"}}, {"id": 159, "dependency_ids": [], "name": "Stop", "namespace": "/", "parameters": {}}, {"id": 160, "dependency_ids": [], "name": "MoveToFrame", "namespace": "/", "parameters": {"zone": -1, "speed": 100.0, "feedback_level": 1, "frame": {"guid": "b9947a54-6265-4a1f-a3c4-634189239d78", "dtype": "compas.geometry/Frame", "value": {"point": [1022.0360664187875, -1195.6752664047699, 643.20230215510696], "yaxis": [-0.57153161038701239, 0.82057196137526378, -0.0036434232777853874], "xaxis": [-0.82055893426219328, -0.57154312232966309, -0.0046362398722901111]}}, "motion_type": "rrc.Motion.LINEAR"}}, {"id": 161, "dependency_ids": [], "name": "MoveToFrame", "namespace": "/", "parameters": {"zone": -1, "speed": 100.0, "feedback_level": 1, "frame": {"guid": "686d8290-a2ce-4103-a019-0a7b20a8a7c0", "dtype": "compas.geometry/Frame", "value": {"point": [1021.7417293207094, -1195.6582721106929, 693.20143291621798], "yaxis": [-0.57153161038701239, 0.82057196137526378, -0.0036434232777853874], "xaxis": [-0.82055893426219328, -0.57154312232966309, -0.0046362398722901111]}}, "motion_type": "rrc.Motion.LINEAR"}}, {"id": 162, "dependency_ids": [], "name": "MoveToJoints", "namespace": "/", "parameters": {"zone": -1, "speed": 100.0, "ext_axes": [], "feedback_level": 1, "joints": [-46.409581405596683, 64.744230849783023, -62.796174346338226, 180.25252234815699, -87.777134214042121, 100.09572680935483]}}, {"id": 163, "dependency_ids": [], "name": "MoveToJoints", "namespace": "/", "parameters": {"zone": 5, "speed": 100.0, "ext_axes": [], "feedback_level": 1, "joints": [-46.409581405596683, 64.744230849783023, -62.796174346338226, 180.25252234815699, -87.777134214042121, 100.09572680935483]}}, {"id": 164, "dependency_ids": [], "name": "MoveToJoints", "namespace": "/", "parameters": {"zone": 5, "speed": 100.0, "ext_axes": [], "feedback_level": 1, "joints": [-48.004693427763563, 62.293158705498641, -59.319518524864016, 182.36481041184868, -84.783337441707872, 100.52639867721005]}}, {"id": 165, "dependency_ids": [], "name": "MoveToJoints", "namespace": "/", "parameters": {"zone": 5, "speed": 100.0, "ext_axes": [], "feedback_level": 1, "joints": [-49.599805449930443, 59.842086561214252, -55.842862703389812, 184.47709847554040, -81.789540669373622, 100.95707054506528]}}, {"id": 166, "dependency_ids": [], "name": "MoveToJoints", "namespace": "/", "parameters": {"zone": 5, "speed": 100.0, "ext_axes": [], "feedback_level": 1, "joints": [-51.194917472097316, 57.391014416929870, -52.366206881915602, 186.58938653923212, -78.795743897039372, 101.38774241292050]}}, {"id": 167, "dependency_ids": [], "name": "MoveToJoints", "namespace": "/", "parameters": {"zone": 5, "speed": 100.0, "ext_axes": [], "feedback_level": 1, "joints": [-52.790029494264203, 54.939942272645489, -48.889551060441399, 188.70167460292382, -75.801947124705123, 101.81841428077573]}}, {"id": 168, "dependency_ids": [], "name": "MoveToJoints", "namespace": "/", "parameters": {"zone": 5, "speed": 100.0, "ext_axes": [], "feedback_level": 1, "joints": [-54.385141516431077, 52.488870128361107, -45.412895238967181, 190.81396266661554, -72.808150352370888, 102.24908614863095]}}, {"id": 169, "dependency_ids": [], "name": "MoveToJoints", "namespace": "/", "parameters": {"zone": 5, "speed": 100.0, "ext_axes": [], "feedback_level": 1, "joints": [-55.980253538597950, 50.037797984076725, -41.936239417492978, 192.92625073030726, -69.814353580036638, 102.67975801648619]}}, {"id": 170, "dependency_ids": [], "name": "MoveToJoints", "namespace": "/", "parameters": {"zone": 5, "speed": 100.0, "ext_axes": [], "feedback_level": 1, "joints": [-57.575365560764844, 47.586725839792344, -38.459583596018760, 195.03853879399895, -66.820556807702403, 103.11042988434141]}}, {"id": 171, "dependency_ids": [], "name": "MoveToJoints", "namespace": "/", "parameters": {"zone": 5, "speed": 100.0, "ext_axes": [], "feedback_level": 1, "joints": [-59.170477582931717, 45.135653695507962, -34.982927774544564, 197.15082685769065, -63.826760035368146, 103.54110175219664]}}, {"id": 172, "dependency_ids": [], "name": "MoveToJoints", "namespace": "/", "parameters": {"zone": 5, "speed": 100.0, "ext_axes": [], "feedback_level": 1, "joints": [-60.765589605098590, 42.684581551223580, -31.506271953070346, 199.26311492138237, -60.832963263033903, 103.97177362005186]}}, {"id": 173, "dependency_ids": [], "name": "MoveToJoints", "namespace": "/", "parameters": {"zone": 5, "speed": 100.0, "ext_axes": [], "feedback_level": 1, "joints": [-62.360701627265470, 40.233509406939199, -28.029616131596139, 201.37540298507406, -57.839166490699654, 104.40244548790709]}}, {"id": 174, "dependency_ids": [], "name": "MoveToJoints", "namespace": "/", "parameters": {"zone": 5, "speed": 100.0, "ext_axes": [], "feedback_level": 1, "joints": [-63.955813649432343, 37.782437262654817, -24.552960310121929, 203.48769104876578, -54.845369718365411, 104.83311735576231]}}, {"id": 175, "dependency_ids": [], "name": "MoveToJoints", "namespace": "/", "parameters": {"zone": 5, "speed": 100.0, "ext_axes": [], "feedback_level": 1, "joints": [-65.550925671599217, 35.331365118370428, -21.076304488647722, 205.59997911245750, -51.851572946031162, 105.26378922361755]}}, {"id": 176, "dependency_ids": [], "name": "MoveToJoints", "namespace": "/", "parameters": {"zone": 5, "speed": 100.0, "ext_axes": [], "feedback_level": 1, "joints": [-67.146037693766104, 32.880292974086053, -17.599648667173511, 207.71226717614920, -48.857776173696912, 105.69446109147277]}}, {"id": 177, "dependency_ids": [], "name": "MoveToJoints", "namespace": "/", "parameters": {"zone": 5, "speed": 100.0, "ext_axes": [], "feedback_level": 1, "joints": [-68.741149715932991, 30.429220829801668, -14.122992845699304, 209.82455523984092, -45.863979401362670, 106.12513295932801]}}, {"id": 178, "dependency_ids": [], "name": "MoveToJoints", "namespace": "/", "parameters": {"zone": 5, "speed": 100.0, "ext_axes": [], "feedback_level": 1, "joints": [-70.336261738099878, 27.978148685517287, -10.646337024225089, 211.93684330353264, -42.870182629028420, 106.55580482718324]}}, {"id": 179, "dependency_ids": [], "name": "MoveToJoints", "namespace": "/", "parameters": {"zone": 5, "speed": 100.0, "ext_axes": [], "feedback_level": 1, "joints": [-71.931373760266752, 25.527076541232901, -7.1696812027508869, 214.04913136722433, -39.876385856694178, 106.98647669503846]}}, {"id": 180, "dependency_ids": [], "name": "MoveToJoints", "namespace": "/", "parameters": {"zone": 5, "speed": 100.0, "ext_axes": [], "feedback_level": 1, "joints": [-73.526485782433625, 23.076004396948520, -3.6930253812766654, 216.16141943091606, -36.882589084359928, 107.41714856289369]}}, {"id": 181, "dependency_ids": [], "name": "MoveToJoints", "namespace": "/", "parameters": {"zone": 5, "speed": 100.0, "ext_axes": [], "feedback_level": 1, "joints": [-75.121597804600498, 20.624932252664141, -0.21636955980246314, 218.27370749460775, -33.888792312025679, 107.84782043074892]}}, {"id": 182, "dependency_ids": [], "name": "MoveToJoints", "namespace": "/", "parameters": {"zone": 5, "speed": 100.0, "ext_axes": [], "feedback_level": 1, "joints": [-76.716709826767371, 18.173860108379753, 3.2602862616717516, 220.38599555829947, -30.894995539691433, 108.27849229860415]}}, {"id": 183, "dependency_ids": [], "name": "MoveToJoints", "namespace": "/", "parameters": {"zone": 5, "speed": 100.0, "ext_axes": [], "feedback_level": 1, "joints": [-78.311821848934258, 15.722787964095374, 6.7369420831459541, 222.49828362199116, -27.901198767357187, 108.70916416645937]}}, {"id": 184, "dependency_ids": [], "name": "MoveToJoints", "namespace": "/", "parameters": {"zone": 5, "speed": 100.0, "ext_axes": [], "feedback_level": 1, "joints": [-79.906933871101131, 13.271715819810991, 10.213597904620169, 224.61057168568286, -24.907401995022937, 109.13983603431460]}}, {"id": 185, "dependency_ids": [], "name": "MoveToJoints", "namespace": "/", "parameters": {"zone": 5, "speed": 100.0, "ext_axes": [], "feedback_level": 1, "joints": [-81.502045893268004, 10.820643675526615, 13.690253726094371, 226.72285974937458, -21.913605222688702, 109.57050790216982]}}, {"id": 186, "dependency_ids": [], "name": "MoveToJoints", "namespace": "/", "parameters": {"zone": 5, "speed": 100.0, "ext_axes": [], "feedback_level": 1, "joints": [-83.097157915434892, 8.3695715312422241, 17.166909547568586, 228.83514781306630, -18.919808450354456, 110.00117977002506]}}, {"id": 187, "dependency_ids": [], "name": "MoveToJoints", "namespace": "/", "parameters": {"zone": 5, "speed": 100.0, "ext_axes": [], "feedback_level": 1, "joints": [-84.692269937601765, 5.9184993869578415, 20.643565369042790, 230.94743587675799, -15.926011678020206, 110.43185163788029]}}, {"id": 188, "dependency_ids": [], "name": "MoveToJoints", "namespace": "/", "parameters": {"zone": 5, "speed": 100.0, "ext_axes": [], "feedback_level": 1, "joints": [-86.287381959768652, 3.4674272426734642, 24.120221190517004, 233.05972394044971, -12.932214905685958, 110.86252350573551]}}, {"id": 189, "dependency_ids": [], "name": "MoveToJoints", "namespace": "/", "parameters": {"zone": 5, "speed": 100.0, "ext_axes": [], "feedback_level": 1, "joints": [-87.882493981935539, 1.0163550983890872, 27.596877011991204, 235.17201200414144, -9.9384181333517105, 111.29319537359073]}}, {"id": 190, "dependency_ids": [], "name": "MoveToJoints", "namespace": "/", "parameters": {"zone": 5, "speed": 100.0, "ext_axes": [], "feedback_level": 1, "joints": [-89.477606004102412, -1.4347170458953078, 31.073532833465425, 237.28430006783313, -6.9446213610174592, 111.72386724144596]}}, {"id": 191, "dependency_ids": [], "name": "MoveToJoints", "namespace": "/", "parameters": {"zone": 5, "speed": 100.0, "ext_axes": [], "feedback_level": 1, "joints": [-86.265212963448747, -0.0087793792533779509, 30.088972257351642, 233.47103631637924, -10.086977070931328, 111.32975896067570]}}, {"id": 192, "dependency_ids": [], "name": "MoveToJoints", "namespace": "/", "parameters": {"zone": 5, "speed": 100.0, "ext_axes": [], "feedback_level": 1, "joints": [-83.052819922795095, 1.4171582873885520, 29.104411681237849, 229.65777256492538, -13.229332780845196, 110.93565067990545]}}, {"id": 193, "dependency_ids": [], "name": "MoveToJoints", "namespace": "/", "parameters": {"zone": 5, "speed": 100.0, "ext_axes": [], "feedback_level": 1, "joints": [-79.840426882141429, 2.8430959540304817, 28.119851105124063, 225.84450881347149, -16.371688490759066, 110.54154239913520]}}, {"id": 194, "dependency_ids": [], "name": "MoveToJoints", "namespace": "/", "parameters": {"zone": 5, "speed": 100.0, "ext_axes": [], "feedback_level": 1, "joints": [-76.628033841487778, 4.2690336206724115, 27.135290529010273, 222.03124506201760, -19.514044200672934, 110.14743411836496]}}, {"id": 195, "dependency_ids": [], "name": "MoveToJoints", "namespace": "/", "parameters": {"zone": 5, "speed": 100.0, "ext_axes": [], "feedback_level": 1, "joints": [-73.415640800834112, 5.6949712873143419, 26.150729952896487, 218.21798131056372, -22.656399910586799, 109.75332583759470]}}, {"id": 196, "dependency_ids": [], "name": "MoveToJoints", "namespace": "/", "parameters": {"zone": 5, "speed": 100.0, "ext_axes": [], "feedback_level": 1, "joints": [-70.203247760180460, 7.1209089539562713, 25.166169376782697, 214.40471755910983, -25.798755620500671, 109.35921755682443]}}, {"id": 197, "dependency_ids": [], "name": "MoveToJoints", "namespace": "/", "parameters": {"zone": 5, "speed": 100.0, "ext_axes": [], "feedback_level": 1, "joints": [-66.990854719526794, 8.5468466205982008, 24.181608800668911, 210.59145380765597, -28.941111330414540, 108.96510927605418]}}, {"id": 198, "dependency_ids": [], "name": "MoveToJoints", "namespace": "/", "parameters": {"zone": 5, "speed": 100.0, "ext_axes": [], "feedback_level": 1, "joints": [-63.778461678873136, 9.9727842872401311, 23.197048224555122, 206.77819005620205, -32.083467040328408, 108.57100099528392]}}, {"id": 199, "dependency_ids": [], "name": "MoveToJoints", "namespace": "/", "parameters": {"zone": 5, "speed": 100.0, "ext_axes": [], "feedback_level": 1, "joints": [-60.566068638219477, 11.398721953882061, 22.212487648441336, 202.96492630474819, -35.225822750242273, 108.17689271451367]}}, {"id": 200, "dependency_ids": [], "name": "MoveToJoints", "namespace": "/", "parameters": {"zone": 5, "speed": 100.0, "ext_axes": [], "feedback_level": 1, "joints": [-57.353675597565818, 12.824659620523992, 21.227927072327549, 199.15166255329430, -38.368178460156138, 107.78278443374342]}}, {"id": 201, "dependency_ids": [], "name": "MoveToJoints", "namespace": "/", "parameters": {"zone": 5, "speed": 100.0, "ext_axes": [], "feedback_level": 1, "joints": [-54.141282556912159, 14.250597287165920, 20.243366496213756, 195.33839880184041, -41.510534170070009, 107.38867615297318]}}, {"id": 202, "dependency_ids": [], "name": "MoveToJoints", "namespace": "/", "parameters": {"zone": 5, "speed": 100.0, "ext_axes": [], "feedback_level": 1, "joints": [-50.928889516258494, 15.676534953807849, 19.258805920099970, 191.52513505038652, -44.652889879983881, 106.99456787220291]}}, {"id": 203, "dependency_ids": [], "name": "MoveToJoints", "namespace": "/", "parameters": {"zone": 5, "speed": 100.0, "ext_axes": [], "feedback_level": 1, "joints": [-47.716496475604828, 17.102472620449777, 18.274245343986181, 187.71187129893264, -47.795245589897746, 106.60045959143265]}}, {"id": 204, "dependency_ids": [], "name": "MoveToJoints", "namespace": "/", "parameters": {"zone": 5, "speed": 100.0, "ext_axes": [], "feedback_level": 1, "joints": [-44.504103434951169, 18.528410287091710, 17.289684767872394, 183.89860754747878, -50.937601299811618, 106.20635131066240]}}, {"id": 205, "dependency_ids": [], "name": "MoveToJoints", "namespace": "/", "parameters": {"zone": 5, "speed": 100.0, "ext_axes": [], "feedback_level": 1, "joints": [-41.291710394297510, 19.954347953733638, 16.305124191758608, 180.08534379602489, -54.079957009725490, 105.81224302989214]}}, {"id": 206, "dependency_ids": [], "name": "MoveToJoints", "namespace": "/", "parameters": {"zone": -1, "speed": 100.0, "ext_axes": [], "feedback_level": 1, "joints": [-41.252961249419272, 20.511889065683469, 15.412564689019145, 180.25252234815699, -53.800736962784299, 105.13775540650606]}}, {"id": 207, "dependency_ids": [], "name": "MoveToFrame", "namespace": "/", "parameters": {"zone": -1, "speed": 100.0, "feedback_level": 1, "frame": {"guid": "287c6520-33e0-41d6-9df4-0b3980a82698", "dtype": "compas.geometry/Frame", "value": {"point": [822.35019327373868, -577.38811052229676, 691.81750103594266], "yaxis": [0.51207959349141974, 0.85893368628925759, 0.0027225883291156871], "xaxis": [-0.85891782854865717, 0.51208671827644103, -0.0052303695973310409]}}, "motion_type": "rrc.Motion.LINEAR"}}, {"id": 208, "dependency_ids": [], "name": "MoveToFrame", "namespace": "/", "parameters": {"zone": -1, "speed": 100.0, "feedback_level": 1, "frame": {"guid": "a13eecdd-4276-41ae-861b-f0c0ee61a73b", "dtype": "compas.geometry/Frame", "value": {"point": [822.64453037181681, -577.40510481637352, 641.81837027483175], "yaxis": [0.51207959349141974, 0.85893368628925759, 0.0027225883291156871], "xaxis": [-0.85891782854865717, 0.51208671827644103, -0.0052303695973310409]}}, "motion_type": "rrc.Motion.LINEAR"}}, {"id": 209, "dependency_ids": [], "name": "PrintText", "namespace": "/", "parameters": {"text": "Start Cutting Side B-2?"}}, {"id": 210, "dependency_ids": [], "name": "Stop", "namespace": "/", "parameters": {}}, {"id": 211, "dependency_ids": [], "name": "MoveToFrame", "namespace": "/", "parameters": {"zone": -1, "speed": 100.0, "feedback_level": 1, "frame": {"guid": "ce0761fb-2d2a-45c6-bd5e-55aa64d1e4a9", "dtype": "compas.geometry/Frame", "value": {"point": [1108.4103355653231, -987.69108550400551, 643.64008191372443], "yaxis": [0.51207959349141974, 0.85893368628925759, 0.0027225883291156871], "xaxis": [-0.85891782854865717, 0.51208671827644103, -0.0052303695973310409]}}, "motion_type": "rrc.Motion.LINEAR"}}, {"id": 212, "dependency_ids": [], "name": "MoveToFrame", "namespace": "/", "parameters": {"zone": -1, "speed": 100.0, "feedback_level": 1, "frame": {"guid": "a7e86b9c-0b3e-40b9-8e81-c45c3adb39ab", "dtype": "compas.geometry/Frame", "value": {"point": [1108.1159984672449, -987.67409120992863, 693.63921267483545], "yaxis": [0.51207959349141974, 0.85893368628925759, 0.0027225883291156871], "xaxis": [-0.85891782854865717, 0.51208671827644103, -0.0052303695973310409]}}, "motion_type": "rrc.Motion.LINEAR"}}, {"id": 213, "dependency_ids": [], "name": "MoveToJoints", "namespace": "/", "parameters": {"zone": -1, "speed": 100.0, "ext_axes": [], "feedback_level": 1, "joints": [-46.409581405596683, 64.744230849783023, -62.796174346338226, 180.25252234815699, -87.777134214042121, 100.09572680935483]}}, {"id": 214, "dependency_ids": [], "name": "PrintText", "namespace": "/", "parameters": {"text": "Robot Goes to place"}}, {"id": 215, "dependency_ids": [], "name": "Stop", "namespace": "/", "parameters": {}}, {"id": 216, "dependency_ids": [], "name": "MoveToJoints", "namespace": "/", "parameters": {"zone": 5, "speed": 100.0, "ext_axes": [], "feedback_level": 1, "joints": [-46.409581405596683, 64.744230849783023, -62.796174346338226, 180.25252234815699, -87.777134214042121, 100.09572680935483]}}, {"id": 217, "dependency_ids": [], "name": "MoveToJoints", "namespace": "/", "parameters": {"zone": 5, "speed": 100.0, "ext_axes": [], "feedback_level": 1, "joints": [-46.854865605240072, 63.168050031527898, -60.965459129367567, 183.88443206884202, -85.574484056743543, 103.35687305169790]}}, {"id": 218, "dependency_ids": [], "name": "MoveToJoints", "namespace": "/", "parameters": {"zone": 5, "speed": 100.0, "ext_axes": [], "feedback_level": 1, "joints": [-47.300149804883461, 61.591869213272766, -59.134743912396907, 187.51634178952705, -83.371833899444965, 106.61801929404098]}}, {"id": 219, "dependency_ids": [], "name": "MoveToJoints", "namespace": "/", "parameters": {"zone": 5, "speed": 100.0, "ext_axes": [], "feedback_level": 1, "joints": [-47.745434004526835, 60.015688395017641, -57.304028695426226, 191.14825151021208, -81.169183742146373, 109.87916553638405]}}, {"id": 220, "dependency_ids": [], "name": "MoveToJoints", "namespace": "/", "parameters": {"zone": 5, "speed": 100.0, "ext_axes": [], "feedback_level": 1, "joints": [-48.190718204170224, 58.439507576762509, -55.473313478455566, 194.78016123089714, -78.966533584847795, 113.14031177872712]}}, {"id": 221, "dependency_ids": [], "name": "MoveToJoints", "namespace": "/", "parameters": {"zone": 5, "speed": 100.0, "ext_axes": [], "feedback_level": 1, "joints": [-48.636002403813613, 56.863326758507384, -53.642598261484906, 198.41207095158217, -76.763883427549217, 116.40145802107021]}}, {"id": 222, "dependency_ids": [], "name": "MoveToJoints", "namespace": "/", "parameters": {"zone": 5, "speed": 100.0, "ext_axes": [], "feedback_level": 1, "joints": [-49.081286603456995, 55.287145940252259, -51.811883044514232, 202.04398067226722, -74.561233270250625, 119.66260426341329]}}, {"id": 223, "dependency_ids": [], "name": "MoveToJoints", "namespace": "/", "parameters": {"zone": 5, "speed": 100.0, "ext_axes": [], "feedback_level": 1, "joints": [-49.526570803100384, 53.710965121997134, -49.981167827543572, 205.67589039295225, -72.358583112952047, 122.92375050575636]}}, {"id": 224, "dependency_ids": [], "name": "MoveToJoints", "namespace": "/", "parameters": {"zone": 5, "speed": 100.0, "ext_axes": [], "feedback_level": 1, "joints": [-49.971855002743773, 52.134784303742002, -48.150452610572898, 209.30780011363728, -70.155932955653455, 126.18489674809945]}}, {"id": 225, "dependency_ids": [], "name": "MoveToJoints", "namespace": "/", "parameters": {"zone": 5, "speed": 100.0, "ext_axes": [], "feedback_level": 1, "joints": [-50.417139202387155, 50.558603485486884, -46.319737393602239, 212.93970983432231, -67.953282798354877, 129.44604299044252]}}, {"id": 226, "dependency_ids": [], "name": "MoveToJoints", "namespace": "/", "parameters": {"zone": 5, "speed": 100.0, "ext_axes": [], "feedback_level": 1, "joints": [-50.862423402030537, 48.982422667231752, -44.489022176631579, 216.57161955500737, -65.750632641056299, 132.70718923278559]}}, {"id": 227, "dependency_ids": [], "name": "MoveToJoints", "namespace": "/", "parameters": {"zone": 5, "speed": 100.0, "ext_axes": [], "feedback_level": 1, "joints": [-51.307707601673926, 47.406241848976627, -42.658306959660898, 220.20352927569240, -63.547982483757714, 135.96833547512867]}}, {"id": 228, "dependency_ids": [], "name": "MoveToJoints", "namespace": "/", "parameters": {"zone": 5, "speed": 100.0, "ext_axes": [], "feedback_level": 1, "joints": [-51.752991801317314, 45.830061030721502, -40.827591742690238, 223.83543899637743, -61.345332326459143, 139.22948171747177]}}, {"id": 229, "dependency_ids": [], "name": "MoveToJoints", "namespace": "/", "parameters": {"zone": 5, "speed": 100.0, "ext_axes": [], "feedback_level": 1, "joints": [-52.198276000960696, 44.253880212466377, -38.996876525719571, 227.46734871706249, -59.142682169160551, 142.49062795981482]}}, {"id": 230, "dependency_ids": [], "name": "MoveToJoints", "namespace": "/", "parameters": {"zone": 5, "speed": 100.0, "ext_axes": [], "feedback_level": 1, "joints": [-52.643560200604085, 42.677699394211253, -37.166161308748912, 231.09925843774752, -56.940032011861973, 145.75177420215789]}}, {"id": 231, "dependency_ids": [], "name": "MoveToJoints", "namespace": "/", "parameters": {"zone": 5, "speed": 100.0, "ext_axes": [], "feedback_level": 1, "joints": [-53.088844400247474, 41.101518575956121, -35.335446091778245, 234.73116815843258, -54.737381854563395, 149.01292044450096]}}, {"id": 232, "dependency_ids": [], "name": "MoveToJoints", "namespace": "/", "parameters": {"zone": 5, "speed": 100.0, "ext_axes": [], "feedback_level": 1, "joints": [-53.534128599890849, 39.525337757700996, -33.504730874807578, 238.36307787911758, -52.534731697264817, 152.27406668684407]}}, {"id": 233, "dependency_ids": [], "name": "MoveToJoints", "namespace": "/", "parameters": {"zone": 5, "speed": 100.0, "ext_axes": [], "feedback_level": 1, "joints": [-53.979412799534238, 37.949156939445871, -31.674015657836911, 241.99498759980264, -50.332081539966232, 155.53521292918714]}}, {"id": 234, "dependency_ids": [], "name": "MoveToJoints", "namespace": "/", "parameters": {"zone": 5, "speed": 100.0, "ext_axes": [], "feedback_level": 1, "joints": [-54.424696999177627, 36.372976121190746, -29.843300440866248, 245.62689732048764, -48.129431382667654, 158.79635917153021]}}, {"id": 235, "dependency_ids": [], "name": "MoveToJoints", "namespace": "/", "parameters": {"zone": 5, "speed": 100.0, "ext_axes": [], "feedback_level": 1, "joints": [-54.869981198821009, 34.796795302935614, -28.012585223895577, 249.25880704117270, -45.926781225369069, 162.05750541387329]}}, {"id": 236, "dependency_ids": [], "name": "MoveToJoints", "namespace": "/", "parameters": {"zone": 5, "speed": 100.0, "ext_axes": [], "feedback_level": 1, "joints": [-54.254423841576774, 33.457993381754079, -26.168700300264099, 252.44187544170151, -43.886354360041665, 165.53957265263344]}}, {"id": 237, "dependency_ids": [], "name": "MoveToJoints", "namespace": "/", "parameters": {"zone": 5, "speed": 100.0, "ext_axes": [], "feedback_level": 1, "joints": [-53.638866484332524, 32.119191460572544, -24.324815376632621, 255.62494384223027, -41.845927494714275, 169.02163989139365]}}, {"id": 238, "dependency_ids": [], "name": "MoveToJoints", "namespace": "/", "parameters": {"zone": 5, "speed": 100.0, "ext_axes": [], "feedback_level": 1, "joints": [-53.023309127088282, 30.780389539391006, -22.480930453001147, 258.80801224275905, -39.805500629386884, 172.50370713015380]}}, {"id": 239, "dependency_ids": [], "name": "MoveToJoints", "namespace": "/", "parameters": {"zone": 5, "speed": 100.0, "ext_axes": [], "feedback_level": 1, "joints": [-52.407751769844033, 29.441587618209468, -20.637045529369669, 261.99108064328789, -37.765073764059487, 175.98577436891395]}}, {"id": 240, "dependency_ids": [], "name": "MoveToJoints", "namespace": "/", "parameters": {"zone": 5, "speed": 100.0, "ext_axes": [], "feedback_level": 1, "joints": [-51.792194412599791, 28.102785697027930, -18.793160605738191, 265.17414904381661, -35.724646898732090, 179.46784160767416]}}, {"id": 241, "dependency_ids": [], "name": "MoveToJoints", "namespace": "/", "parameters": {"zone": 5, "speed": 100.0, "ext_axes": [], "feedback_level": 1, "joints": [-51.176637055355542, 26.763983775846391, -16.949275682106716, 268.35721744434545, -33.684220033404699, 182.94990884643431]}}, {"id": 242, "dependency_ids": [], "name": "MoveToJoints", "namespace": "/", "parameters": {"zone": 5, "speed": 100.0, "ext_axes": [], "feedback_level": 1, "joints": [-50.561079698111300, 25.425181854664856, -15.105390758475238, 271.54028584487423, -31.643793168077305, 186.43197608519446]}}, {"id": 243, "dependency_ids": [], "name": "MoveToJoints", "namespace": "/", "parameters": {"zone": 5, "speed": 100.0, "ext_axes": [], "feedback_level": 1, "joints": [-49.945522340867058, 24.086379933483318, -13.26150583484376, 274.72335424540296, -29.603366302749905, 189.91404332395464]}}, {"id": 244, "dependency_ids": [], "name": "MoveToJoints", "namespace": "/", "parameters": {"zone": 5, "speed": 100.0, "ext_axes": [], "feedback_level": 1, "joints": [-49.329964983622816, 22.747578012301780, -11.417620911212284, 277.90642264593180, -27.562939437422511, 193.39611056271482]}}, {"id": 245, "dependency_ids": [], "name": "MoveToJoints", "namespace": "/", "parameters": {"zone": 5, "speed": 100.0, "ext_axes": [], "feedback_level": 1, "joints": [-48.265422903437660, 21.477665736643900, -9.5013902952784761, 280.98607148486752, -25.496641524893136, 197.10496433847447]}}, {"id": 246, "dependency_ids": [], "name": "MoveToJoints", "namespace": "/", "parameters": {"zone": 5, "speed": 100.0, "ext_axes": [], "feedback_level": 1, "joints": [-47.200880823252504, 20.207753460986023, -7.5851596793446685, 284.06572032380325, -23.430343612363757, 200.81381811423415]}}, {"id": 247, "dependency_ids": [], "name": "MoveToJoints", "namespace": "/", "parameters": {"zone": 5, "speed": 100.0, "ext_axes": [], "feedback_level": 1, "joints": [-46.136338743067348, 18.937841185328139, -5.6689290634108618, 287.14536916273886, -21.364045699834382, 204.52267188999383]}}, {"id": 248, "dependency_ids": [], "name": "MoveToJoints", "namespace": "/", "parameters": {"zone": 5, "speed": 100.0, "ext_axes": [], "feedback_level": 1, "joints": [-45.071796662882200, 17.667928909670263, -3.7526984474770542, 290.22501800167458, -19.297747787305006, 208.23152566575348]}}, {"id": 249, "dependency_ids": [], "name": "MoveToJoints", "namespace": "/", "parameters": {"zone": 5, "speed": 100.0, "ext_axes": [], "feedback_level": 1, "joints": [-44.007254582697051, 16.398016634012379, -1.8364678315432463, 293.30466684061031, -17.231449874775628, 211.94037944151313]}}, {"id": 250, "dependency_ids": [], "name": "MoveToJoints", "namespace": "/", "parameters": {"zone": 5, "speed": 100.0, "ext_axes": [], "feedback_level": 1, "joints": [-42.942712502511895, 15.128104358354499, 0.079762784390560101, 296.38431567954598, -15.165151962246254, 215.64923321727281]}}, {"id": 251, "dependency_ids": [], "name": "MoveToJoints", "namespace": "/", "parameters": {"zone": 5, "speed": 100.0, "ext_axes": [], "feedback_level": 1, "joints": [-41.878170422326740, 13.858192082696618, 1.9959934003243665, 299.46396451848170, -13.098854049716875, 219.35808699303249]}}, {"id": 252, "dependency_ids": [], "name": "MoveToJoints", "namespace": "/", "parameters": {"zone": 5, "speed": 100.0, "ext_axes": [], "feedback_level": 1, "joints": [-40.813628342141584, 12.588279807038738, 3.9122240162581727, 302.54361335741743, -11.032556137187500, 223.06694076879216]}}, {"id": 253, "dependency_ids": [], "name": "MoveToJoints", "namespace": "/", "parameters": {"zone": 5, "speed": 100.0, "ext_axes": [], "feedback_level": 1, "joints": [-37.826144710514825, 12.319909277298748, 5.7974012167752091, 300.33013866441593, -13.283607355713626, 221.58206819896756]}}, {"id": 254, "dependency_ids": [], "name": "MoveToJoints", "namespace": "/", "parameters": {"zone": 5, "speed": 100.0, "ext_axes": [], "feedback_level": 1, "joints": [-34.838661078888066, 12.051538747558759, 7.6825784172922447, 298.11666397141437, -15.534658574239753, 220.09719562914293]}}, {"id": 255, "dependency_ids": [], "name": "MoveToJoints", "namespace": "/", "parameters": {"zone": 5, "speed": 100.0, "ext_axes": [], "feedback_level": 1, "joints": [-31.851177447261303, 11.783168217818771, 9.5677556178092793, 295.90318927841287, -17.785709792765875, 218.61232305931833]}}, {"id": 256, "dependency_ids": [], "name": "MoveToJoints", "namespace": "/", "parameters": {"zone": 5, "speed": 100.0, "ext_axes": [], "feedback_level": 1, "joints": [-28.863693815634541, 11.514797688078781, 11.452932818326317, 293.68971458541131, -20.036761011292004, 217.12745048949370]}}, {"id": 257, "dependency_ids": [], "name": "MoveToJoints", "namespace": "/", "parameters": {"zone": 5, "speed": 100.0, "ext_axes": [], "feedback_level": 1, "joints": [-25.876210184007785, 11.246427158338792, 13.338110018843352, 291.47623989240981, -22.287812229818130, 215.64257791966909]}}, {"id": 258, "dependency_ids": [], "name": "MoveToJoints", "namespace": "/", "parameters": {"zone": 5, "speed": 100.0, "ext_axes": [], "feedback_level": 1, "joints": [-21.312830585621629, 13.398944900976174, 13.397031700783774, 288.10165260539378, -21.511507311749899, 218.06747700221115]}}, {"id": 259, "dependency_ids": [], "name": "MoveToJoints", "namespace": "/", "parameters": {"zone": 5, "speed": 100.0, "ext_axes": [], "feedback_level": 1, "joints": [-16.749450987235473, 15.551462643613558, 13.455953382724198, 284.72706531837781, -20.735202393681671, 220.49237608475315]}}, {"id": 260, "dependency_ids": [], "name": "MoveToJoints", "namespace": "/", "parameters": {"zone": 5, "speed": 100.0, "ext_axes": [], "feedback_level": 1, "joints": [-12.186071388849314, 17.703980386250944, 13.514875064664620, 281.35247803136190, -19.958897475613444, 222.91727516729520]}}, {"id": 261, "dependency_ids": [], "name": "MoveToJoints", "namespace": "/", "parameters": {"zone": 5, "speed": 100.0, "ext_axes": [], "feedback_level": 1, "joints": [-7.6226917904631577, 19.856498128888322, 13.573796746605042, 277.97789074434587, -19.182592557545217, 225.34217424983726]}}, {"id": 262, "dependency_ids": [], "name": "MoveToJoints", "namespace": "/", "parameters": {"zone": 5, "speed": 100.0, "ext_axes": [], "feedback_level": 1, "joints": [-3.0593121920769981, 22.009015871525705, 13.632718428545466, 274.60330345732990, -18.406287639476986, 227.76707333237928]}}, {"id": 263, "dependency_ids": [], "name": "MoveToJoints", "namespace": "/", "parameters": {"zone": 5, "speed": 100.0, "ext_axes": [], "feedback_level": 1, "joints": [1.5040674063091581, 24.161533614163091, 13.691640110485888, 271.22871617031387, -17.629982721408759, 230.19197241492131]}}, {"id": 264, "dependency_ids": [], "name": "MoveToJoints", "namespace": "/", "parameters": {"zone": 5, "speed": 100.0, "ext_axes": [], "feedback_level": 1, "joints": [6.0674470046953175, 26.314051356800476, 13.750561792426312, 267.85412888329790, -16.853677803340531, 232.61687149746334]}}, {"id": 265, "dependency_ids": [], "name": "MoveToJoints", "namespace": "/", "parameters": {"zone": 5, "speed": 100.0, "ext_axes": [], "feedback_level": 1, "joints": [10.630826603081470, 28.466569099437855, 13.809483474366735, 264.47954159628199, -16.077372885272304, 235.04177058000539]}}, {"id": 266, "dependency_ids": [], "name": "MoveToJoints", "namespace": "/", "parameters": {"zone": 5, "speed": 100.0, "ext_axes": [], "feedback_level": 1, "joints": [15.194206201467637, 30.619086842075237, 13.868405156307157, 261.10495430926596, -15.301067967204071, 237.46666966254742]}}, {"id": 267, "dependency_ids": [], "name": "MoveToJoints", "namespace": "/", "parameters": {"zone": 5, "speed": 100.0, "ext_axes": [], "feedback_level": 1, "joints": [19.757585799853789, 32.771604584712620, 13.927326838247581, 257.73036702224999, -14.524763049135846, 239.89156874508950]}}, {"id": 268, "dependency_ids": [], "name": "MoveToJoints", "namespace": "/", "parameters": {"zone": 5, "speed": 100.0, "ext_axes": [], "feedback_level": 1, "joints": [24.320965398239949, 34.924122327350005, 13.986248520188003, 254.35577973523399, -13.748458131067615, 242.31646782763150]}}, {"id": 269, "dependency_ids": [], "name": "MoveToJoints", "namespace": "/", "parameters": {"zone": 5, "speed": 100.0, "ext_axes": [], "feedback_level": 1, "joints": [28.884344996626101, 37.076640069987384, 14.045170202128427, 250.98119244821800, -12.972153212999388, 244.74136691017353]}}, {"id": 270, "dependency_ids": [], "name": "MoveToJoints", "namespace": "/", "parameters": {"zone": 5, "speed": 100.0, "ext_axes": [], "feedback_level": 1, "joints": [33.447724595012261, 39.229157812624777, 14.104091884068849, 247.60660516120200, -12.195848294931158, 247.16626599271561]}}, {"id": 271, "dependency_ids": [], "name": "MoveToJoints", "namespace": "/", "parameters": {"zone": 5, "speed": 100.0, "ext_axes": [], "feedback_level": 1, "joints": [38.011104193398417, 41.381675555262156, 14.163013566009271, 244.23201787418606, -11.419543376862929, 249.59116507525761]}}, {"id": 272, "dependency_ids": [], "name": "MoveToJoints", "namespace": "/", "parameters": {"zone": 5, "speed": 100.0, "ext_axes": [], "feedback_level": 1, "joints": [42.574483791784580, 43.534193297899549, 14.221935247949695, 240.85743058717009, -10.643238458794702, 252.01606415779963]}}, {"id": 273, "dependency_ids": [], "name": "MoveToJoints", "namespace": "/", "parameters": {"zone": 5, "speed": 100.0, "ext_axes": [], "feedback_level": 1, "joints": [47.137863390170729, 45.686711040536927, 14.280856929890117, 237.48284330015409, -9.8669335407264747, 254.44096324034172]}}, {"id": 274, "dependency_ids": [], "name": "MoveToJoints", "namespace": "/", "parameters": {"zone": 5, "speed": 100.0, "ext_axes": [], "feedback_level": 1, "joints": [51.701242988556885, 47.839228783174306, 14.339778611830539, 234.10825601313815, -9.0906286226582456, 256.86586232288374]}}, {"id": 275, "dependency_ids": [], "name": "MoveToJoints", "namespace": "/", "parameters": {"zone": 5, "speed": 100.0, "ext_axes": [], "feedback_level": 1, "joints": [56.264622586943055, 49.991746525811692, 14.398700293770963, 230.73366872612215, -8.3143237045900165, 259.29076140542577]}}, {"id": 276, "dependency_ids": [], "name": "MoveToJoints", "namespace": "/", "parameters": {"zone": 5, "speed": 100.0, "ext_axes": [], "feedback_level": 1, "joints": [60.828002185329211, 52.144264268449071, 14.457621975711385, 227.35908143910618, -7.5380187865217891, 261.71566048796780]}}, {"id": 277, "dependency_ids": [], "name": "MoveToJoints", "namespace": "/", "parameters": {"zone": 5, "speed": 100.0, "ext_axes": [], "feedback_level": 1, "joints": [65.391381783715360, 54.296782011086449, 14.516543657651811, 223.98449415209018, -6.7617138684535609, 264.14055957050982]}}, {"id": 278, "dependency_ids": [], "name": "MoveToJoints", "namespace": "/", "parameters": {"zone": 5, "speed": 100.0, "ext_axes": [], "feedback_level": 1, "joints": [69.954761382101509, 56.449299753723842, 14.575465339592231, 220.60990686507418, -5.9854089503853327, 266.56545865305185]}}, {"id": 279, "dependency_ids": [], "name": "MoveToJoints", "namespace": "/", "parameters": {"zone": 5, "speed": 100.0, "ext_axes": [], "feedback_level": 1, "joints": [74.518140980487672, 58.601817496361221, 14.634387021532653, 217.23531957805818, -5.2091040323171018, 268.99035773559393]}}, {"id": 280, "dependency_ids": [], "name": "MoveToJoints", "namespace": "/", "parameters": {"zone": 5, "speed": 100.0, "ext_axes": [], "feedback_level": 1, "joints": [79.081520578873821, 60.754335238998614, 14.693308703473077, 213.86073229104221, -4.4327991142488736, 271.41525681813596]}}, {"id": 281, "dependency_ids": [], "name": "MoveToJoints", "namespace": "/", "parameters": {"zone": 5, "speed": 100.0, "ext_axes": [], "feedback_level": 1, "joints": [83.644900177259998, 62.906852981635993, 14.752230385413499, 210.48614500402627, -3.6564941961806481, 273.84015590067798]}}, {"id": 282, "dependency_ids": [], "name": "MoveToJoints", "namespace": "/", "parameters": {"zone": 5, "speed": 100.0, "ext_axes": [], "feedback_level": 1, "joints": [88.208279775646147, 65.059370724273364, 14.811152067353923, 207.11155771701027, -2.8801892781124199, 276.26505498322001]}}, {"id": 283, "dependency_ids": [], "name": "MoveToJoints", "namespace": "/", "parameters": {"zone": 5, "speed": 100.0, "ext_axes": [], "feedback_level": 1, "joints": [92.771659374032311, 67.211888466910764, 14.870073749294345, 203.73697042999427, -2.1038843600441886, 278.68995406576204]}}, {"id": 284, "dependency_ids": [], "name": "MoveToJoints", "namespace": "/", "parameters": {"zone": 5, "speed": 100.0, "ext_axes": [], "feedback_level": 1, "joints": [97.335038972418459, 69.364406209548136, 14.928995431234767, 200.36238314297827, -1.3275794419759606, 281.11485314830412]}}, {"id": 285, "dependency_ids": [], "name": "MoveToJoints", "namespace": "/", "parameters": {"zone": 5, "speed": 100.0, "ext_axes": [], "feedback_level": 1, "joints": [101.89841857080464, 71.516923952185522, 14.987917113175191, 196.98779585596230, -0.55127452390773235, 283.53975223084615]}}, {"id": 286, "dependency_ids": [], "name": "MoveToJoints", "namespace": "/", "parameters": {"zone": 5, "speed": 100.0, "ext_axes": [], "feedback_level": 1, "joints": [106.46179816919079, 73.669441694822908, 15.046838795115614, 193.61320856894636, 0.22503039416049267, 285.96465131338817]}}, {"id": 287, "dependency_ids": [], "name": "MoveToJoints", "namespace": "/", "parameters": {"zone": 5, "speed": 100.0, "ext_axes": [], "feedback_level": 1, "joints": [111.02517776757695, 75.821959437460293, 15.105760477056037, 190.23862128193036, 1.0013353122287241, 288.38955039593020]}}, {"id": 288, "dependency_ids": [], "name": "MoveToJoints", "namespace": "/", "parameters": {"zone": 5, "speed": 100.0, "ext_axes": [], "feedback_level": 1, "joints": [115.58855736596310, 77.974477180097679, 15.164682158996460, 186.86403399491437, 1.7776402302969530, 290.81444947847223]}}, {"id": 289, "dependency_ids": [], "name": "MoveToFrame", "namespace": "/", "parameters": {"zone": -1, "speed": 100.0, "feedback_level": 1, "frame": {"guid": "c58791ad-0cc4-44bd-b1e4-ba893f29cf77", "dtype": "compas.geometry/Frame", "value": {"point": [-498.16305925504139, 949.29356586561187, -345.98659493599155], "yaxis": [-0.012195677474881548, 0.99992554522150801, -0.00041166053837515348], "xaxis": [-0.99990830165571021, -0.012197888795103912, -0.0058821585269071084]}}, "motion_type": "rrc.Motion.LINEAR"}}, {"id": 290, "dependency_ids": [], "name": "MoveToFrame", "namespace": "/", "parameters": {"zone": -1, "speed": 100.0, "feedback_level": 1, "frame": {"guid": "c993d8bb-49f5-442f-90f4-5bdb79eecdce", "dtype": "compas.geometry/Frame", "value": {"point": [-497.57438505888467, 949.25957727745833, -445.98485645821336], "yaxis": [-0.012195677474881548, 0.99992554522150801, -0.00041166053837515348], "xaxis": [-0.99990830165571021, -0.012197888795103912, -0.0058821585269071084]}}, "motion_type": "rrc.Motion.LINEAR"}}, {"id": 291, "dependency_ids": [], "name": "PrintText", "namespace": "/", "parameters": {"text": "Unscrew the beam!"}}, {"id": 292, "dependency_ids": [], "name": "Stop", "namespace": "/", "parameters": {}}, {"id": 293, "dependency_ids": [], "name": "SetDigital", "namespace": "/", "parameters": {"io_name": "Local_IO_0_DO1", "value": 1}}, {"id": 294, "dependency_ids": [], "name": "WaitTime", "namespace": "/", "parameters": {"time": 0.5, "feedback_level": 1}}, {"id": 295, "dependency_ids": [], "name": "MoveToFrame", "namespace": "/", "parameters": {"zone": -1, "speed": 100.0, "feedback_level": 1, "frame": {"guid": "e921e16d-d08b-4279-a3d4-de20e542d88f", "dtype": "compas.geometry/Frame", "value": {"point": [-498.16305925504139, 949.29356586561187, -345.98659493599155], "yaxis": [-0.012195677474881548, 0.99992554522150801, -0.00041166053837515348], "xaxis": [-0.99990830165571021, -0.012197888795103912, -0.0058821585269071084]}}, "motion_type": "rrc.Motion.LINEAR"}}, {"id": 296, "dependency_ids": [], "name": "PrintText", "namespace": "/", "parameters": {"text": "Robot Goes to pick next element"}}, {"id": 297, "dependency_ids": [], "name": "Stop", "namespace": "/", "parameters": {}}, {"id": 298, "dependency_ids": [], "name": "MoveToJoints", "namespace": "/", "parameters": {"zone": 5, "speed": 100.0, "ext_axes": [], "feedback_level": 1, "joints": [115.45763244727428, 78.419020321038047, 14.495182229002115, 186.11227562483157, 2.7637240433085992, 290.05168668606376]}}, {"id": 299, "dependency_ids": [], "name": "MoveToJoints", "namespace": "/", "parameters": {"zone": 5, "speed": 100.0, "ext_axes": [], "feedback_level": 1, "joints": [110.66435654241666, 76.609173605362329, 15.396628233751834, 185.94115169126553, 1.8560482579183031, 285.41692677211392]}}, {"id": 300, "dependency_ids": [], "name": "MoveToJoints", "namespace": "/", "parameters": {"zone": 5, "speed": 100.0, "ext_axes": [], "feedback_level": 1, "joints": [105.87108063755905, 74.799326889686625, 16.298074238501552, 185.77002775769949, 0.94837247252800627, 280.78216685816398]}}, {"id": 301, "dependency_ids": [], "name": "MoveToJoints", "namespace": "/", "parameters": {"zone": 5, "speed": 100.0, "ext_axes": [], "feedback_level": 1, "joints": [101.07780473270142, 72.989480174010893, 17.199520243251271, 185.59890382413346, 0.040696687137709617, 276.14740694421408]}}, {"id": 302, "dependency_ids": [], "name": "MoveToJoints", "namespace": "/", "parameters": {"zone": 5, "speed": 100.0, "ext_axes": [], "feedback_level": 1, "joints": [96.284528827843815, 71.179633458335189, 18.100966248000990, 185.42777989056742, -0.86697909825258668, 271.51264703026419]}}, {"id": 303, "dependency_ids": [], "name": "MoveToJoints", "namespace": "/", "parameters": {"zone": 5, "speed": 100.0, "ext_axes": [], "feedback_level": 1, "joints": [91.491252922986192, 69.369786742659471, 19.002412252750709, 185.25665595700141, -1.7746548836428833, 266.87788711631430]}}, {"id": 304, "dependency_ids": [], "name": "MoveToJoints", "namespace": "/", "parameters": {"zone": 5, "speed": 100.0, "ext_axes": [], "feedback_level": 1, "joints": [86.697977018128569, 67.559940026983767, 19.903858257500428, 185.08553202343538, -2.6823306690331798, 262.24312720236446]}}, {"id": 305, "dependency_ids": [], "name": "MoveToJoints", "namespace": "/", "parameters": {"zone": 5, "speed": 100.0, "ext_axes": [], "feedback_level": 1, "joints": [81.904701113270960, 65.750093311308035, 20.805304262250147, 184.91440808986934, -3.5900064544234764, 257.60836728841451]}}, {"id": 306, "dependency_ids": [], "name": "MoveToJoints", "namespace": "/", "parameters": {"zone": 5, "speed": 100.0, "ext_axes": [], "feedback_level": 1, "joints": [77.111425208413337, 63.940246595632331, 21.706750266999865, 184.74328415630330, -4.4976822398137726, 252.97360737446465]}}, {"id": 307, "dependency_ids": [], "name": "MoveToJoints", "namespace": "/", "parameters": {"zone": 5, "speed": 100.0, "ext_axes": [], "feedback_level": 1, "joints": [72.318149303555714, 62.130399879956613, 22.608196271749584, 184.57216022273727, -5.4053580252040696, 248.33884746051476]}}, {"id": 308, "dependency_ids": [], "name": "MoveToJoints", "namespace": "/", "parameters": {"zone": 5, "speed": 100.0, "ext_axes": [], "feedback_level": 1, "joints": [67.524873398698105, 60.320553164280902, 23.509642276499303, 184.40103628917129, -6.3130338105943666, 243.70408754656484]}}, {"id": 309, "dependency_ids": [], "name": "MoveToJoints", "namespace": "/", "parameters": {"zone": 5, "speed": 100.0, "ext_axes": [], "feedback_level": 1, "joints": [62.731597493840482, 58.510706448605184, 24.411088281249025, 184.22991235560525, -7.2207095959846646, 239.06932763261497]}}, {"id": 310, "dependency_ids": [], "name": "MoveToJoints", "namespace": "/", "parameters": {"zone": 5, "speed": 100.0, "ext_axes": [], "feedback_level": 1, "joints": [57.938321588982873, 56.700859732929473, 25.312534285998744, 184.05878842203921, -8.1283853813749598, 234.43456771866505]}}, {"id": 311, "dependency_ids": [], "name": "MoveToJoints", "namespace": "/", "parameters": {"zone": 5, "speed": 100.0, "ext_axes": [], "feedback_level": 1, "joints": [53.145045684125250, 54.891013017253748, 26.213980290748463, 183.88766448847318, -9.0360611667652577, 229.79980780471516]}}, {"id": 312, "dependency_ids": [], "name": "MoveToJoints", "namespace": "/", "parameters": {"zone": 5, "speed": 100.0, "ext_axes": [], "feedback_level": 1, "joints": [48.351769779267627, 53.081166301578044, 27.115426295498178, 183.71654055490714, -9.9437369521555539, 225.16504789076527]}}, {"id": 313, "dependency_ids": [], "name": "MoveToJoints", "namespace": "/", "parameters": {"zone": 5, "speed": 100.0, "ext_axes": [], "feedback_level": 1, "joints": [43.558493874410011, 51.271319585902319, 28.016872300247901, 183.54541662134113, -10.851412737545850, 220.53028797681537]}}, {"id": 314, "dependency_ids": [], "name": "MoveToJoints", "namespace": "/", "parameters": {"zone": 5, "speed": 100.0, "ext_axes": [], "feedback_level": 1, "joints": [38.765217969552403, 49.461472870226608, 28.918318304997616, 183.37429268777510, -11.759088522936144, 215.89552806286551]}}, {"id": 315, "dependency_ids": [], "name": "MoveToJoints", "namespace": "/", "parameters": {"zone": 5, "speed": 100.0, "ext_axes": [], "feedback_level": 1, "joints": [33.971942064694780, 47.651626154550890, 29.819764309747335, 183.20316875420906, -12.666764308326442, 211.26076814891559]}}, {"id": 316, "dependency_ids": [], "name": "MoveToJoints", "namespace": "/", "parameters": {"zone": 5, "speed": 100.0, "ext_axes": [], "feedback_level": 1, "joints": [29.178666159837167, 45.841779438875179, 30.721210314497053, 183.03204482064302, -13.574440093716738, 206.62600823496570]}}, {"id": 317, "dependency_ids": [], "name": "MoveToJoints", "namespace": "/", "parameters": {"zone": 5, "speed": 100.0, "ext_axes": [], "feedback_level": 1, "joints": [24.385390254979548, 44.031932723199461, 31.622656319246776, 182.86092088707701, -14.482115879107035, 201.99124832101580]}}, {"id": 318, "dependency_ids": [], "name": "MoveToJoints", "namespace": "/", "parameters": {"zone": 5, "speed": 100.0, "ext_axes": [], "feedback_level": 1, "joints": [19.592114350121939, 42.222086007523750, 32.524102323996487, 182.68979695351098, -15.389791664497331, 197.35648840706591]}}, {"id": 319, "dependency_ids": [], "name": "MoveToJoints", "namespace": "/", "parameters": {"zone": 5, "speed": 100.0, "ext_axes": [], "feedback_level": 1, "joints": [14.798838445264304, 40.412239291848024, 33.425548328746217, 182.51867301994494, -16.297467449887630, 192.72172849311599]}}, {"id": 320, "dependency_ids": [], "name": "MoveToJoints", "namespace": "/", "parameters": {"zone": 5, "speed": 100.0, "ext_axes": [], "feedback_level": 1, "joints": [10.005562540406695, 38.602392576172313, 34.326994333495932, 182.34754908637890, -17.205143235277927, 188.08696857916610]}}, {"id": 321, "dependency_ids": [], "name": "MoveToJoints", "namespace": "/", "parameters": {"zone": 5, "speed": 100.0, "ext_axes": [], "feedback_level": 1, "joints": [5.2122866355490851, 36.792545860496602, 35.228440338245655, 182.17642515281287, -18.112819020668223, 183.45220866521623]}}, {"id": 322, "dependency_ids": [], "name": "MoveToJoints", "namespace": "/", "parameters": {"zone": 5, "speed": 100.0, "ext_axes": [], "feedback_level": 1, "joints": [0.41901073069147582, 34.982699144820884, 36.129886342995363, 182.00530121924686, -19.020494806058515, 178.81744875126637]}}, {"id": 323, "dependency_ids": [], "name": "MoveToJoints", "namespace": "/", "parameters": {"zone": 5, "speed": 100.0, "ext_axes": [], "feedback_level": 1, "joints": [-4.3742651741661591, 33.172852429145166, 37.031332347745092, 181.83417728568082, -19.928170591448815, 174.18268883731642]}}, {"id": 324, "dependency_ids": [], "name": "MoveToJoints", "namespace": "/", "parameters": {"zone": 5, "speed": 100.0, "ext_axes": [], "feedback_level": 1, "joints": [-9.1675410790237670, 31.363005713469452, 37.932778352494807, 181.66305335211479, -20.835846376839115, 169.54792892336653]}}, {"id": 325, "dependency_ids": [], "name": "MoveToJoints", "namespace": "/", "parameters": {"zone": 5, "speed": 100.0, "ext_axes": [], "feedback_level": 1, "joints": [-13.960816983881378, 29.553158997793741, 38.834224357244523, 181.49192941854875, -21.743522162229407, 164.91316900941666]}}, {"id": 326, "dependency_ids": [], "name": "MoveToJoints", "namespace": "/", "parameters": {"zone": 5, "speed": 100.0, "ext_axes": [], "feedback_level": 1, "joints": [-18.754092888739013, 27.743312282118026, 39.735670361994245, 181.32080548498271, -22.651197947619703, 160.27840909546677]}}, {"id": 327, "dependency_ids": [], "name": "MoveToJoints", "namespace": "/", "parameters": {"zone": 5, "speed": 100.0, "ext_axes": [], "feedback_level": 1, "joints": [-23.547368793596622, 25.933465566442305, 40.637116366743967, 181.14968155141673, -23.558873733010003, 155.64364918151685]}}, {"id": 328, "dependency_ids": [], "name": "MoveToJoints", "namespace": "/", "parameters": {"zone": 5, "speed": 100.0, "ext_axes": [], "feedback_level": 1, "joints": [-28.340644698454255, 24.123618850766590, 41.538562371493683, 180.97855761785070, -24.466549518400296, 151.00888926756696]}}, {"id": 329, "dependency_ids": [], "name": "MoveToJoints", "namespace": "/", "parameters": {"zone": 5, "speed": 100.0, "ext_axes": [], "feedback_level": 1, "joints": [-33.133920603311864, 22.313772135090883, 42.440008376243398, 180.80743368428466, -25.374225303790592, 146.37412935361709]}}, {"id": 330, "dependency_ids": [], "name": "MoveToJoints", "namespace": "/", "parameters": {"zone": 5, "speed": 100.0, "ext_axes": [], "feedback_level": 1, "joints": [-37.927196508169473, 20.503925419415161, 43.341454380993113, 180.63630975071862, -26.281901089180888, 141.73936943966720]}}, {"id": 331, "dependency_ids": [], "name": "MoveToJoints", "namespace": "/", "parameters": {"zone": 5, "speed": 100.0, "ext_axes": [], "feedback_level": 1, "joints": [-42.720472413027110, 18.694078703739439, 44.242900385742843, 180.46518581715259, -27.189576874571188, 137.10460952571728]}}, {"id": 332, "dependency_ids": [], "name": "MoveToJoints", "namespace": "/", "parameters": {"zone": 5, "speed": 100.0, "ext_axes": [], "feedback_level": 1, "joints": [-47.513748317884719, 16.884231988063732, 45.144346390492558, 180.29406188358658, -28.097252659961484, 132.46984961176739]}}, {"id": 333, "dependency_ids": [], "name": "MoveToJoints", "namespace": "/", "parameters": {"zone": 5, "speed": 100.0, "ext_axes": [], "feedback_level": 1, "joints": [-52.307024222742328, 15.074385272388023, 46.045792395242273, 180.12293795002054, -29.004928445351780, 127.83508969781752]}}, {"id": 334, "dependency_ids": [], "name": "MoveToJoints", "namespace": "/", "parameters": {"zone": 5, "speed": 100.0, "ext_axes": [], "feedback_level": 1, "joints": [-57.100300127599937, 13.264538556712301, 46.947238399991996, 179.95181401645451, -29.912604230742073, 123.20032978386762]}}, {"id": 335, "dependency_ids": [], "name": "MoveToJoints", "namespace": "/", "parameters": {"zone": 5, "speed": 100.0, "ext_axes": [], "feedback_level": 1, "joints": [-61.893576032457567, 11.454691841036579, 47.848684404741718, 179.78069008288847, -30.820280016132376, 118.56556986991772]}}, {"id": 336, "dependency_ids": [], "name": "MoveToJoints", "namespace": "/", "parameters": {"zone": 5, "speed": 100.0, "ext_axes": [], "feedback_level": 1, "joints": [-66.686851937315183, 9.6448451253608738, 48.750130409491433, 179.60956614932243, -31.727955801522668, 113.93080995596782]}}]}